Workbook

Sheet history
A1: snapshot_date | B1: snapshot_ts | C1: carrier | D1: category | E1: state | F1: plan_name | G1: plan_id | H1: price_brl | I1: price_promo_brl | J1: price_note | K1: payment_method | L1: data_gb | M1: data_note | N1: validity_days | O1: unlimited_apps | P1: voice | Q1: sms | R1: streaming | S1: loyalty_months | T1: extra_benefits | U1: source_url | V1: raw_ref
A2: 2026-06-22 | B2: 2026-06-22T22:45:24 | C2: claro | D2: control | E2: SP | F2: Controle 25GB | G2: claro:plano-controle-25gb | H2: 59.9 | I2: 54.9 | J2: De R$ 59,90 Por: | L2: 25 | O2: WhatsApp | T2: Para uso livre; Para redes sociais e vídeos; Bônus exclusivo; Aproveite na sua franquia; WhatsApp e ligações ilimitadas | U2: https://www.claro.com.br/celular/controle | V2: data/raw/claro_control_SP.json
A3: 2026-06-22 | B3: 2026-06-22T22:45:24 | C3: claro | D3: control | E3: SP | F3: Controle 30GB | G3: claro:plano-controle-30gb | H3: 69.9 | L3: 30 | O3: WhatsApp | T3: Para uso livre; Bônus do Hexa para uso livre; Bônus para redes sociais e apps; Redes sociais e apps; WhatsApp ilimitado | U3: https://www.claro.com.br/celular/controle | V3: data/raw/claro_control_SP.json
A4: 2026-06-22 | B4: 2026-06-22T22:45:24 | C4: claro | D4: control | E4: SP | F4: Controle 30GB | G4: claro:plano-controle-30gb-gaming | H4: 99.9 | L4: 30 | O4: WhatsApp | T4: Para uso livre; Bônus para redes sociais e apps; Bônus uso livre; Redes sociais e apps; WhatsApp ilimitado | U4: https://www.claro.com.br/celular/controle | V4: data/raw/claro_control_SP.json
A5: 2026-06-22 | B5: 2026-06-22T22:45:24 | C5: claro | D5: flex | E5: SP | F5: Flex 15GB | G5: claro:plano-flex-15gb | H5: 44.9 | L5: 15 | O5: WhatsApp | T5: Para uso livre; Bônus do Hexa para uso livre; Para redes sociais e apps; Bônus extra nos apps; WhatsApp ilimitado | U5: https://www.claro.com.br/celular/flex | V5: data/raw/claro_flex_SP.json
A6: 2026-06-22 | B6: 2026-06-22T22:45:24 | C6: claro | D6: flex | E6: SP | F6: Flex 20GB | G6: claro:plano-flex-20gb | H6: 59.9 | L6: 20 | O6: WhatsApp | T6: Para uso livre; Bônus do Hexa para uso livre; Para redes sociais e apps; Bônus extra nos apps; WhatsApp ilimitado | U6: https://www.claro.com.br/celular/flex | V6: data/raw/claro_flex_SP.json
A7: 2026-06-22 | B7: 2026-06-22T22:45:24 | C7: claro | D7: flex | E7: SP | F7: Flex 30GB | G7: claro:plano-flex-30gb | H7: 69.9 | L7: 30 | O7: WhatsApp | T7: Para uso livre; Bônus do Hexa para uso livre; Para redes sociais e apps; Bônus extra nos apps; WhatsApp ilimitado; Assinatura Claro musica inclusa | U7: https://www.claro.com.br/celular/flex | V7: data/raw/claro_flex_SP.json
A8: 2026-06-22 | B8: 2026-06-22T22:45:24 | C8: claro | D8: flex | E8: SP | F8: Flex 40GB | G8: claro:plano-flex-40gb | H8: 119.9 | L8: 40 | O8: WhatsApp | T8: Para uso livre; Para redes sociais e apps; Bônus uso livre; Bônus extra nos apps; WhatsApp ilimitado; Assinatura Claro musica inclusa | U8: https://www.claro.com.br/celular/flex | V8: data/raw/claro_flex_SP.json
A9: 2026-06-22 | B9: 2026-06-22T22:45:24 | C9: claro | D9: postpaid | E9: SP | F9: Pós 100GB | G9: claro:plano-pos-100gb | H9: 179.9 | L9: 100 | O9: WhatsApp | T9: Armazenamento na nuvem:; Google One ou iCloud+; WhatsApp ilimitado; Roaming: Passaporte Américas; Claro Sync: Smartwatch conectado | U9: https://www.claro.com.br/celular/pos | V9: data/raw/claro_postpaid_SP.json
A10: 2026-06-22 | B10: 2026-06-22T22:45:24 | C10: claro | D10: postpaid | E10: SP | F10: Pós 150GB | G10: claro:plano-pos-150gb | H10: 239.9 | L10: 150 | O10: WhatsApp | T10: Armazenamento na nuvem:; Google One ou iCloud+; WhatsApp ilimitado; Roaming: Passaporte Américas e Europa; Claro Sync: Smartwatch conectado | U10: https://www.claro.com.br/celular/pos | V10: data/raw/claro_postpaid_SP.json
A11: 2026-06-22 | B11: 2026-06-22T22:45:24 | C11: claro | D11: postpaid | E11: SP | F11: Pós 200GB | G11: claro:plano-pos-200gb | H11: 339.9 | L11: 200 | O11: WhatsApp | T11: Armazenamento na nuvem:; Google One ou iCloud+; WhatsApp ilimitado; Roaming: Passaporte Mundo; Claro Sync: Smartwatch conectado | U11: https://www.claro.com.br/celular/pos | V11: data/raw/claro_postpaid_SP.json
A12: 2026-06-22 | B12: 2026-06-22T22:45:24 | C12: claro | D12: postpaid | E12: SP | F12: Pós 50GB com GeForce NOW | G12: claro:plano-pos-60gb-geforce | H12: 164.9 | L12: 50 | O12: WhatsApp | T12: Armazenamento na nuvem:; Google One ou iCloud+; WhatsApp ilimitado; Roaming: Passaporte Américas; Claro Sync: Smartwatch conectado; Inclusa assinatura GeForce NOW | U12: https://www.claro.com.br/celular/pos | V12: data/raw/claro_postpaid_SP.json
A13: 2026-06-22 | B13: 2026-06-22T22:45:24 | C13: claro | D13: postpaid | E13: SP | F13: Pós 60GB | G13: claro:plano-pos-60gb | H13: 124.9 | L13: 60 | O13: WhatsApp | T13: Armazenamento na nuvem:; Google One ou iCloud+; WhatsApp ilimitado; Roaming: Passaporte Américas; Claro Sync: Smartwatch conectado | U13: https://www.claro.com.br/celular/pos | V13: data/raw/claro_postpaid_SP.json
A14: 2026-06-22 | B14: 2026-06-22T22:45:24 | C14: claro | D14: prepaid | E14: SP | F14: Prezão R$1 por dia | G14: claro:prez-o-r-1-por-dia | H14: 1 | J14: prepaid Prezão — preço por dia; recargas a partir de R$15 | L14: 12 | U14: https://www.claro.com.br/celular/planos-pre/prezao | V14: data/raw/claro_prepaid_SP.json
A15: 2026-06-22 | B15: 2026-06-22T22:45:24 | C15: tim | D15: control | E15: SP | F15: TIM Controle 41GB | G15: tim:162901 | H15: 58.99 | L15: 41 | U15: https://www.tim.com.br/sp/para-voce/planos/controle | V15: data/raw/tim_control_SP.html
A16: 2026-06-22 | B16: 2026-06-22T22:45:24 | C16: tim | D16: control | E16: SP | F16: TIM Controle Light Express 31GB | G16: tim:143536 | H16: 60.99 | L16: 31 | U16: https://www.tim.com.br/sp/para-voce/planos/controle | V16: data/raw/tim_control_SP.html
A17: 2026-06-22 | B17: 2026-06-22T22:45:24 | C17: tim | D17: control | E17: SP | F17: TIM Controle Plus 45GB | G17: tim:155891 | H17: 64.99 | L17: 45 | U17: https://www.tim.com.br/sp/para-voce/planos/controle | V17: data/raw/tim_control_SP.html
A18: 2026-06-22 | B18: 2026-06-22T22:45:24 | C18: tim | D18: control | E18: SP | F18: TIM Controle Premium 53GB | G18: tim:162896 | H18: 84.99 | L18: 53 | U18: https://www.tim.com.br/sp/para-voce/planos/controle | V18: data/raw/tim_control_SP.html
A19: 2026-06-22 | B19: 2026-06-22T22:45:24 | C19: tim | D19: control | E19: SP | F19: TIM Controle Pro Express | G19: tim:143576 | H19: 64.99 | U19: https://www.tim.com.br/sp/para-voce/planos/controle | V19: data/raw/tim_control_SP.html
A20: 2026-06-22 | B20: 2026-06-22T22:45:24 | C20: tim | D20: postpaid | E20: SP | F20: TIM Black 70GB | G20: tim:54206 | H20: 129.99 | L20: 70 | U20: https://www.tim.com.br/sp/para-voce/planos/pos-pago/tim-black | V20: data/raw/tim_postpaid_SP.html
A21: 2026-06-22 | B21: 2026-06-22T22:45:24 | C21: tim | D21: postpaid | E21: SP | F21: TIM Black A Express 67GB | G21: tim:55121 | H21: 119.99 | L21: 67 | U21: https://www.tim.com.br/sp/para-voce/planos/pos-pago/tim-black | V21: data/raw/tim_postpaid_SP.html
A22: 2026-06-22 | B22: 2026-06-22T22:45:24 | C22: tim | D22: postpaid | E22: SP | F22: TIM Black B Express 82GB | G22: tim:52146 | H22: 144.99 | L22: 82 | U22: https://www.tim.com.br/sp/para-voce/planos/pos-pago/tim-black | V22: data/raw/tim_postpaid_SP.html
A23: 2026-06-22 | B23: 2026-06-22T22:45:24 | C23: tim | D23: postpaid | E23: SP | F23: TIM Black C Express 107GB | G23: tim:52151 | H23: 164.99 | L23: 107 | U23: https://www.tim.com.br/sp/para-voce/planos/pos-pago/tim-black | V23: data/raw/tim_postpaid_SP.html
A24: 2026-06-22 | B24: 2026-06-22T22:45:24 | C24: tim | D24: postpaid | E24: SP | F24: TIM Black C Ultra 95GB | G24: tim:100581 | H24: 159.99 | L24: 95 | U24: https://www.tim.com.br/sp/para-voce/planos/pos-pago/tim-black | V24: data/raw/tim_postpaid_SP.html
A25: 2026-06-22 | B25: 2026-06-22T22:45:24 | C25: tim | D25: postpaid | E25: SP | F25: TIM Black Plus 80GB | G25: tim:54256 | H25: 149.99 | L25: 80 | U25: https://www.tim.com.br/sp/para-voce/planos/pos-pago/tim-black | V25: data/raw/tim_postpaid_SP.html
A26: 2026-06-22 | B26: 2026-06-22T22:45:24 | C26: tim | D26: postpaid | E26: SP | F26: TIM Black Premium 110GB | G26: tim:54261 | H26: 159.99 | L26: 110 | U26: https://www.tim.com.br/sp/para-voce/planos/pos-pago/tim-black | V26: data/raw/tim_postpaid_SP.html
A27: 2026-06-22 | B27: 2026-06-22T22:45:24 | C27: tim | D27: prepaid | E27: SP | F27: TIM Pré XIP Plus 16GB | G27: tim:106306 | H27: 30 | L27: 16 | U27: https://www.tim.com.br/sp/para-voce/planos/pre-pago | V27: data/raw/tim_prepaid_SP.html
A28: 2026-06-22 | B28: 2026-06-22T22:45:24 | C28: tim | D28: prepaid | E28: SP | F28: TIM Pré XIP Plus 6GB | G28: tim:59906 | H28: 20 | L28: 6 | U28: https://www.tim.com.br/sp/para-voce/planos/pre-pago | V28: data/raw/tim_prepaid_SP.html
A29: 2026-06-22 | B29: 2026-06-22T22:45:24 | C29: tim | D29: prepaid | E29: SP | F29: TIM Pré XIP Plus 8GB | G29: tim:59901 | H29: 25 | L29: 8 | U29: https://www.tim.com.br/sp/para-voce/planos/pre-pago | V29: data/raw/tim_prepaid_SP.html
A30: 2026-06-22 | B30: 2026-06-22T22:45:24 | C30: vivo | D30: control | E30: SP | F30: Vivo Controle | G30: vivo:VIV202600029270-46gb | H30: 59 | L30: 46 | M30: 15 GB de franquia 31 GB de bônus | T30: 6 meses grátis de Gemini com AI Plus | U30: https://vivo.com.br/para-voce/produtos-e-servicos/para-o-celular/planos-controle | V30: data/raw/vivo_control_SP.html
A31: 2026-06-22 | B31: 2026-06-22T22:45:24 | C31: vivo | D31: control | E31: SP | F31: Vivo Controle | G31: vivo:VIV202600029300-61gb | H31: 80 | L31: 61 | M31: 20 GB de franquia 31 GB de bônus | T31: 6 meses grátis de Gemini com AI Plus | U31: https://vivo.com.br/para-voce/produtos-e-servicos/para-o-celular/planos-controle | V31: data/raw/vivo_control_SP.html
A32: 2026-06-22 | B32: 2026-06-22T22:45:24 | C32: vivo | D32: control | E32: SP | F32: Vivo Controle Educação | G32: vivo:VIV202600029273-61gb | H32: 90 | L32: 61 | M32: 20 GB de franquia 31 GB de bônus | T32: Assinatura Vivae inclusa | U32: https://vivo.com.br/para-voce/produtos-e-servicos/para-o-celular/planos-controle | V32: data/raw/vivo_control_SP.html
A33: 2026-06-22 | B33: 2026-06-22T22:45:24 | C33: vivo | D33: control | E33: SP | F33: Vivo Controle Entretenimento | G33: vivo:VIV202600029307-61gb | H33: 110 | L33: 61 | M33: 20 GB de franquia 31 GB de bônus | T33: Assinatura Vivo TV Inicial inclusa | U33: https://vivo.com.br/para-voce/produtos-e-servicos/para-o-celular/planos-controle | V33: data/raw/vivo_control_SP.html
A34: 2026-06-22 | B34: 2026-06-22T22:45:24 | C34: vivo | D34: control | E34: SP | F34: Vivo Controle Música | G34: vivo:VIV202600029313-61gb | H34: 95 | L34: 61 | M34: 20 GB de franquia 31 GB de bônus | T34: Apple Music Individual | U34: https://vivo.com.br/para-voce/produtos-e-servicos/para-o-celular/planos-controle | V34: data/raw/vivo_control_SP.html
A35: 2026-06-22 | B35: 2026-06-22T22:45:24 | C35: vivo | D35: control | E35: SP | F35: Vivo Controle Netflix | G35: vivo:VIV202600029308-61gb | H35: 95 | L35: 61 | M35: 20 GB de franquia 31 GB de bônus | T35: Assinatura Netflix Padrão com anúncios | U35: https://vivo.com.br/para-voce/produtos-e-servicos/para-o-celular/planos-controle | V35: data/raw/vivo_control_SP.html
A36: 2026-06-22 | B36: 2026-06-22T22:45:24 | C36: vivo | D36: control | E36: SP | F36: Vivo Controle Saúde | G36: vivo:VIV202600029301-61gb | H36: 90 | L36: 61 | M36: 20 GB de franquia 31 GB de bônus | T36: Assinatura Vale Saúde Sempre inclusa | U36: https://vivo.com.br/para-voce/produtos-e-servicos/para-o-celular/planos-controle | V36: data/raw/vivo_control_SP.html
A37: 2026-06-22 | B37: 2026-06-22T22:45:24 | C37: vivo | D37: lite | E37: SP | F37: Easy Lite | G37: vivo:VIV202600005312-30gb | H37: 30 | L37: 30 | M37: 30 GB de franquia 2 Meses de YouTube ilimitado | U37: https://vivo.com.br/para-voce/produtos-e-servicos/para-o-celular/easy-lite | V37: data/raw/vivo_lite_SP.html
A38: 2026-06-22 | B38: 2026-06-22T22:45:24 | C38: vivo | D38: lite | E38: SP | F38: Easy Lite | G38: vivo:VIV202600019134-40gb | H38: 40 | L38: 40 | M38: 40 GB de franquia 2 Meses de YouTube ilimitado | U38: https://vivo.com.br/para-voce/produtos-e-servicos/para-o-celular/easy-lite | V38: data/raw/vivo_lite_SP.html
A39: 2026-06-22 | B39: 2026-06-22T22:45:24 | C39: vivo | D39: lite | E39: SP | F39: Easy Lite | G39: vivo:VIV202600019132-20gb | H39: 35 | L39: 20 | M39: 20 GB de franquia 2 Meses de YouTube ilimitado | U39: https://vivo.com.br/para-voce/produtos-e-servicos/para-o-celular/easy-lite | V39: data/raw/vivo_lite_SP.html
A40: 2026-06-22 | B40: 2026-06-22T22:45:24 | C40: vivo | D40: lite | E40: SP | F40: Easy Lite | G40: vivo:VIV202600019127-30gb | H40: 40 | L40: 30 | U40: https://vivo.com.br/para-voce/produtos-e-servicos/para-o-celular/easy-lite | V40: data/raw/vivo_lite_SP.html
A41: 2026-06-22 | B41: 2026-06-22T22:45:24 | C41: vivo | D41: lite | E41: SP | F41: Easy Lite | G41: vivo:VIV202600019129-40gb | H41: 50 | L41: 40 | U41: https://vivo.com.br/para-voce/produtos-e-servicos/para-o-celular/easy-lite | V41: data/raw/vivo_lite_SP.html
A42: 2026-06-22 | B42: 2026-06-22T22:45:24 | C42: vivo | D42: postpaid | E42: SP | F42: Vivo Pós com Amazon | G42: vivo:VIV202600029255-60gb | H42: 150 | L42: 60 | M42: 50 GB de franquia 10 GB de bônus | T42: Assinatura Amazon Prime inclusa | U42: https://vivo.com.br/para-voce/produtos-e-servicos/para-o-celular/planos-pos-pago | V42: data/raw/vivo_postpaid_SP.html
A43: 2026-06-22 | B43: 2026-06-22T22:45:24 | C43: vivo | D43: postpaid | E43: SP | F43: Vivo Pós com Disney+ | G43: vivo:VIV202600022115-60gb | H43: 180 | L43: 60 | M43: 50 GB de franquia 10 GB de bônus | R43: Disney+ | T43: Assinatura Disney+ Padrão inclusa | U43: https://vivo.com.br/para-voce/produtos-e-servicos/para-o-celular/planos-pos-pago | V43: data/raw/vivo_postpaid_SP.html
A44: 2026-06-22 | B44: 2026-06-22T22:45:24 | C44: vivo | D44: postpaid | E44: SP | F44: Vivo Pós com Globoplay | G44: vivo:VIV202600029246-60gb | H44: 165 | L44: 60 | M44: 50 GB de franquia 10 GB de bônus | R44: Globoplay | T44: Assinatura Globoplay inclusa | U44: https://vivo.com.br/para-voce/produtos-e-servicos/para-o-celular/planos-pos-pago | V44: data/raw/vivo_postpaid_SP.html
A45: 2026-06-22 | B45: 2026-06-22T22:45:24 | C45: vivo | D45: postpaid | E45: SP | F45: Vivo Pós com Netflix | G45: vivo:VIV202600029234-60gb | H45: 180 | L45: 60 | M45: 50 GB de franquia 10 GB de bônus | R45: Netflix | T45: Assinatura Netflix Padrão inclusa | U45: https://vivo.com.br/para-voce/produtos-e-servicos/para-o-celular/planos-pos-pago | V45: data/raw/vivo_postpaid_SP.html
A46: 2026-06-22 | B46: 2026-06-22T22:45:24 | C46: vivo | D46: postpaid | E46: SP | F46: Vivo Pós com Premiere | G46: vivo:VIV202600029249-60gb | H46: 180 | L46: 60 | M46: 50 GB de franquia 10 GB de bônus | R46: Premiere | T46: Assinatura Premiere inclusa | U46: https://vivo.com.br/para-voce/produtos-e-servicos/para-o-celular/planos-pos-pago | V46: data/raw/vivo_postpaid_SP.html
A47: 2026-06-22 | B47: 2026-06-22T22:45:24 | C47: vivo | D47: postpaid | E47: SP | F47: Vivo Pós com Spotify | G47: vivo:VIV202600029229-60gb | H47: 165 | L47: 60 | M47: 50 GB de franquia 10 GB de bônus | R47: Spotify | T47: Assinatura Spotify Premium inclusa | U47: https://vivo.com.br/para-voce/produtos-e-servicos/para-o-celular/planos-pos-pago | V47: data/raw/vivo_postpaid_SP.html
A48: 2026-06-22 | B48: 2026-06-22T22:45:24 | C48: vivo | D48: postpaid | E48: SP | F48: Vivo Pós com Travel | G48: vivo:VIV202600029244-70gb | H48: 215 | L48: 70 | M48: 60 GB de franquia 10 GB de bônus | T48: 6 meses grátis de Gemini com AI Plus | U48: https://vivo.com.br/para-voce/produtos-e-servicos/para-o-celular/planos-pos-pago | V48: data/raw/vivo_postpaid_SP.html
A49: 2026-06-22 | B49: 2026-06-22T22:45:24 | C49: vivo | D49: prepaid | E49: SP | F49: Vivo Pré | G49: vivo:VIV202600022379-25gb | H49: 30 | L49: 25 | M49: 15 GB para navegar como quiser 5 GB de bônus 5 GB para navegar no Youtube | U49: https://vivo.com.br/para-voce/produtos-e-servicos/para-o-celular/pre-pago/vivo-pre | V49: data/raw/vivo_prepaid_SP.html
A50: 2026-06-22 | B50: 2026-06-22T22:45:24 | C50: vivo | D50: prepaid | E50: SP | F50: Vivo Pré | G50: vivo:VIV202600022379-9gb | H50: 25 | L50: 9 | M50: 6 GB para navegar como quiser 3 GB para navegar no YouTube | U50: https://vivo.com.br/para-voce/produtos-e-servicos/para-o-celular/pre-pago/vivo-pre | V50: data/raw/vivo_prepaid_SP.html
A51: 2026-06-22 | B51: 2026-06-22T22:45:24 | C51: vivo | D51: prepaid | E51: SP | F51: Vivo Pré | G51: vivo:VIV202600022379-5gb | H51: 20 | L51: 5 | M51: 5 GB para navegar como quiser | U51: https://vivo.com.br/para-voce/produtos-e-servicos/para-o-celular/pre-pago/vivo-pre | V51: data/raw/vivo_prepaid_SP.html
A52: 2026-06-22 | B52: 2026-06-22T22:45:24 | C52: vivo | D52: prepaid | E52: SP | F52: Vivo Pré | G52: vivo:VIV202600022379-4gb | H52: 17 | L52: 4 | M52: 4 GB para navegar como quiser | U52: https://vivo.com.br/para-voce/produtos-e-servicos/para-o-celular/pre-pago/vivo-pre | V52: data/raw/vivo_prepaid_SP.html
A53: 2026-06-23 | B53: 2026-06-23T22:10:23 | C53: claro | D53: control | E53: SP | F53: Controle 25GB | G53: claro:plano-controle-25gb | H53: 59.9 | I53: 54.9 | J53: De R$ 59,90 Por: | L53: 25 | O53: WhatsApp | T53: Para uso livre; Para redes sociais e vídeos; Bônus exclusivo; Aproveite na sua franquia; WhatsApp e ligações ilimitadas | U53: https://www.claro.com.br/celular/controle | V53: data/raw/claro_control_SP.json
A54: 2026-06-23 | B54: 2026-06-23T22:10:23 | C54: claro | D54: control | E54: SP | F54: Controle 30GB | G54: claro:plano-controle-30gb | H54: 69.9 | L54: 30 | O54: WhatsApp | T54: Para uso livre; Bônus do Hexa para uso livre; Bônus para redes sociais e apps; Redes sociais e apps; WhatsApp ilimitado | U54: https://www.claro.com.br/celular/controle | V54: data/raw/claro_control_SP.json
A55: 2026-06-23 | B55: 2026-06-23T22:10:23 | C55: claro | D55: control | E55: SP | F55: Controle 30GB | G55: claro:plano-controle-30gb-gaming | H55: 99.9 | L55: 30 | O55: WhatsApp | T55: Para uso livre; Bônus para redes sociais e apps; Bônus uso livre; Redes sociais e apps; WhatsApp ilimitado | U55: https://www.claro.com.br/celular/controle | V55: data/raw/claro_control_SP.json
A56: 2026-06-23 | B56: 2026-06-23T22:10:23 | C56: claro | D56: flex | E56: SP | F56: Flex 15GB | G56: claro:plano-flex-15gb | H56: 44.9 | L56: 15 | O56: WhatsApp | T56: Para uso livre; Bônus do Hexa para uso livre; Para redes sociais e apps; Bônus extra nos apps; WhatsApp ilimitado | U56: https://www.claro.com.br/celular/flex | V56: data/raw/claro_flex_SP.json
A57: 2026-06-23 | B57: 2026-06-23T22:10:23 | C57: claro | D57: flex | E57: SP | F57: Flex 20GB | G57: claro:plano-flex-20gb | H57: 59.9 | L57: 20 | O57: WhatsApp | T57: Para uso livre; Bônus do Hexa para uso livre; Para redes sociais e apps; Bônus extra nos apps; WhatsApp ilimitado | U57: https://www.claro.com.br/celular/flex | V57: data/raw/claro_flex_SP.json
A58: 2026-06-23 | B58: 2026-06-23T22:10:23 | C58: claro | D58: flex | E58: SP | F58: Flex 30GB | G58: claro:plano-flex-30gb | H58: 69.9 | L58: 30 | O58: WhatsApp | T58: Para uso livre; Bônus do Hexa para uso livre; Para redes sociais e apps; Bônus extra nos apps; WhatsApp ilimitado; Assinatura Claro musica inclusa | U58: https://www.claro.com.br/celular/flex | V58: data/raw/claro_flex_SP.json
A59: 2026-06-23 | B59: 2026-06-23T22:10:23 | C59: claro | D59: flex | E59: SP | F59: Flex 40GB | G59: claro:plano-flex-40gb | H59: 119.9 | L59: 40 | O59: WhatsApp | T59: Para uso livre; Para redes sociais e apps; Bônus uso livre; Bônus extra nos apps; WhatsApp ilimitado; Assinatura Claro musica inclusa | U59: https://www.claro.com.br/celular/flex | V59: data/raw/claro_flex_SP.json
A60: 2026-06-23 | B60: 2026-06-23T22:10:23 | C60: claro | D60: postpaid | E60: SP | F60: Pós 100GB | G60: claro:plano-pos-100gb | H60: 179.9 | L60: 100 | O60: WhatsApp | T60: Armazenamento na nuvem:; Google One ou iCloud+; WhatsApp ilimitado; Roaming: Passaporte Américas; Claro Sync: Smartwatch conectado | U60: https://www.claro.com.br/celular/pos | V60: data/raw/claro_postpaid_SP.json
A61: 2026-06-23 | B61: 2026-06-23T22:10:23 | C61: claro | D61: postpaid | E61: SP | F61: Pós 150GB | G61: claro:plano-pos-150gb | H61: 239.9 | L61: 150 | O61: WhatsApp | T61: Armazenamento na nuvem:; Google One ou iCloud+; WhatsApp ilimitado; Roaming: Passaporte Américas e Europa; Claro Sync: Smartwatch conectado | U61: https://www.claro.com.br/celular/pos | V61: data/raw/claro_postpaid_SP.json
A62: 2026-06-23 | B62: 2026-06-23T22:10:23 | C62: claro | D62: postpaid | E62: SP | F62: Pós 200GB | G62: claro:plano-pos-200gb | H62: 339.9 | L62: 200 | O62: WhatsApp | T62: Armazenamento na nuvem:; Google One ou iCloud+; WhatsApp ilimitado; Roaming: Passaporte Mundo; Claro Sync: Smartwatch conectado | U62: https://www.claro.com.br/celular/pos | V62: data/raw/claro_postpaid_SP.json
A63: 2026-06-23 | B63: 2026-06-23T22:10:23 | C63: claro | D63: postpaid | E63: SP | F63: Pós 50GB com GeForce NOW | G63: claro:plano-pos-60gb-geforce | H63: 164.9 | L63: 50 | O63: WhatsApp | T63: Armazenamento na nuvem:; Google One ou iCloud+; WhatsApp ilimitado; Roaming: Passaporte Américas; Claro Sync: Smartwatch conectado; Inclusa assinatura GeForce NOW | U63: https://www.claro.com.br/celular/pos | V63: data/raw/claro_postpaid_SP.json
A64: 2026-06-23 | B64: 2026-06-23T22:10:23 | C64: claro | D64: postpaid | E64: SP | F64: Pós 60GB | G64: claro:plano-pos-60gb | H64: 124.9 | L64: 60 | O64: WhatsApp | T64: Armazenamento na nuvem:; Google One ou iCloud+; WhatsApp ilimitado; Roaming: Passaporte Américas; Claro Sync: Smartwatch conectado | U64: https://www.claro.com.br/celular/pos | V64: data/raw/claro_postpaid_SP.json
A65: 2026-06-23 | B65: 2026-06-23T22:10:23 | C65: claro | D65: prepaid | E65: SP | F65: Prezão R$1 por dia | G65: claro:prez-o-r-1-por-dia | H65: 1 | J65: prepaid Prezão — preço por dia; recargas a partir de R$15 | L65: 12 | U65: https://www.claro.com.br/celular/planos-pre/prezao | V65: data/raw/claro_prepaid_SP.json
A66: 2026-06-23 | B66: 2026-06-23T22:10:23 | C66: tim | D66: control | E66: SP | F66: TIM Controle 41GB | G66: tim:162901 | H66: 58.99 | L66: 41 | U66: https://www.tim.com.br/sp/para-voce/planos/controle | V66: data/raw/tim_control_SP.html
A67: 2026-06-23 | B67: 2026-06-23T22:10:23 | C67: tim | D67: control | E67: SP | F67: TIM Controle Light Express 31GB | G67: tim:143536 | H67: 60.99 | L67: 31 | U67: https://www.tim.com.br/sp/para-voce/planos/controle | V67: data/raw/tim_control_SP.html
A68: 2026-06-23 | B68: 2026-06-23T22:10:23 | C68: tim | D68: control | E68: SP | F68: TIM Controle Plus 45GB | G68: tim:155891 | H68: 64.99 | L68: 45 | U68: https://www.tim.com.br/sp/para-voce/planos/controle | V68: data/raw/tim_control_SP.html
A69: 2026-06-23 | B69: 2026-06-23T22:10:23 | C69: tim | D69: control | E69: SP | F69: TIM Controle Premium 53GB | G69: tim:162896 | H69: 84.99 | L69: 53 | U69: https://www.tim.com.br/sp/para-voce/planos/controle | V69: data/raw/tim_control_SP.html
A70: 2026-06-23 | B70: 2026-06-23T22:10:23 | C70: tim | D70: control | E70: SP | F70: TIM Controle Pro Express | G70: tim:143576 | H70: 64.99 | U70: https://www.tim.com.br/sp/para-voce/planos/controle | V70: data/raw/tim_control_SP.html
A71: 2026-06-23 | B71: 2026-06-23T22:10:23 | C71: tim | D71: postpaid | E71: SP | F71: TIM Black 70GB | G71: tim:54206 | H71: 129.99 | L71: 70 | U71: https://www.tim.com.br/sp/para-voce/planos/pos-pago/tim-black | V71: data/raw/tim_postpaid_SP.html
A72: 2026-06-23 | B72: 2026-06-23T22:10:23 | C72: tim | D72: postpaid | E72: SP | F72: TIM Black A Express 67GB | G72: tim:55121 | H72: 119.99 | L72: 67 | U72: https://www.tim.com.br/sp/para-voce/planos/pos-pago/tim-black | V72: data/raw/tim_postpaid_SP.html
A73: 2026-06-23 | B73: 2026-06-23T22:10:23 | C73: tim | D73: postpaid | E73: SP | F73: TIM Black B Express 82GB | G73: tim:52146 | H73: 144.99 | L73: 82 | U73: https://www.tim.com.br/sp/para-voce/planos/pos-pago/tim-black | V73: data/raw/tim_postpaid_SP.html
A74: 2026-06-23 | B74: 2026-06-23T22:10:23 | C74: tim | D74: postpaid | E74: SP | F74: TIM Black C Express 107GB | G74: tim:52151 | H74: 164.99 | L74: 107 | U74: https://www.tim.com.br/sp/para-voce/planos/pos-pago/tim-black | V74: data/raw/tim_postpaid_SP.html
A75: 2026-06-23 | B75: 2026-06-23T22:10:23 | C75: tim | D75: postpaid | E75: SP | F75: TIM Black C Ultra 95GB | G75: tim:100581 | H75: 159.99 | L75: 95 | U75: https://www.tim.com.br/sp/para-voce/planos/pos-pago/tim-black | V75: data/raw/tim_postpaid_SP.html
A76: 2026-06-23 | B76: 2026-06-23T22:10:23 | C76: tim | D76: postpaid | E76: SP | F76: TIM Black Plus 80GB | G76: tim:54256 | H76: 149.99 | L76: 80 | U76: https://www.tim.com.br/sp/para-voce/planos/pos-pago/tim-black | V76: data/raw/tim_postpaid_SP.html
A77: 2026-06-23 | B77: 2026-06-23T22:10:23 | C77: tim | D77: postpaid | E77: SP | F77: TIM Black Premium 110GB | G77: tim:54261 | H77: 159.99 | L77: 110 | U77: https://www.tim.com.br/sp/para-voce/planos/pos-pago/tim-black | V77: data/raw/tim_postpaid_SP.html
A78: 2026-06-23 | B78: 2026-06-23T22:10:23 | C78: tim | D78: prepaid | E78: SP | F78: TIM Pré XIP Plus 16GB | G78: tim:106306 | H78: 30 | L78: 16 | U78: https://www.tim.com.br/sp/para-voce/planos/pre-pago | V78: data/raw/tim_prepaid_SP.html
A79: 2026-06-23 | B79: 2026-06-23T22:10:23 | C79: tim | D79: prepaid | E79: SP | F79: TIM Pré XIP Plus 6GB | G79: tim:59906 | H79: 20 | L79: 6 | U79: https://www.tim.com.br/sp/para-voce/planos/pre-pago | V79: data/raw/tim_prepaid_SP.html
A80: 2026-06-23 | B80: 2026-06-23T22:10:23 | C80: tim | D80: prepaid | E80: SP | F80: TIM Pré XIP Plus 8GB | G80: tim:59901 | H80: 25 | L80: 8 | U80: https://www.tim.com.br/sp/para-voce/planos/pre-pago | V80: data/raw/tim_prepaid_SP.html
A81: 2026-06-23 | B81: 2026-06-23T22:10:23 | C81: vivo | D81: control | E81: SP | F81: Vivo Controle | G81: vivo:VIV202600029270-46gb | H81: 59 | L81: 46 | M81: 15 GB de franquia 31 GB de bônus | T81: 6 meses grátis de Gemini com AI Plus | U81: https://vivo.com.br/para-voce/produtos-e-servicos/para-o-celular/planos-controle | V81: data/raw/vivo_control_SP.html
A82: 2026-06-23 | B82: 2026-06-23T22:10:23 | C82: vivo | D82: control | E82: SP | F82: Vivo Controle | G82: vivo:VIV202600029300-61gb | H82: 80 | L82: 61 | M82: 20 GB de franquia 31 GB de bônus | T82: 6 meses grátis de Gemini com AI Plus | U82: https://vivo.com.br/para-voce/produtos-e-servicos/para-o-celular/planos-controle | V82: data/raw/vivo_control_SP.html
A83: 2026-06-23 | B83: 2026-06-23T22:10:23 | C83: vivo | D83: control | E83: SP | F83: Vivo Controle Educação | G83: vivo:VIV202600029273-61gb | H83: 90 | L83: 61 | M83: 20 GB de franquia 31 GB de bônus | T83: Assinatura Vivae inclusa | U83: https://vivo.com.br/para-voce/produtos-e-servicos/para-o-celular/planos-controle | V83: data/raw/vivo_control_SP.html
A84: 2026-06-23 | B84: 2026-06-23T22:10:23 | C84: vivo | D84: control | E84: SP | F84: Vivo Controle Entretenimento | G84: vivo:VIV202600029307-61gb | H84: 110 | L84: 61 | M84: 20 GB de franquia 31 GB de bônus | T84: Assinatura Vivo TV Inicial inclusa | U84: https://vivo.com.br/para-voce/produtos-e-servicos/para-o-celular/planos-controle | V84: data/raw/vivo_control_SP.html
A85: 2026-06-23 | B85: 2026-06-23T22:10:23 | C85: vivo | D85: control | E85: SP | F85: Vivo Controle Música | G85: vivo:VIV202600029313-61gb | H85: 95 | L85: 61 | M85: 20 GB de franquia 31 GB de bônus | T85: Apple Music Individual | U85: https://vivo.com.br/para-voce/produtos-e-servicos/para-o-celular/planos-controle | V85: data/raw/vivo_control_SP.html
A86: 2026-06-23 | B86: 2026-06-23T22:10:23 | C86: vivo | D86: control | E86: SP | F86: Vivo Controle Netflix | G86: vivo:VIV202600029308-61gb | H86: 95 | L86: 61 | M86: 20 GB de franquia 31 GB de bônus | T86: Assinatura Netflix Padrão com anúncios | U86: https://vivo.com.br/para-voce/produtos-e-servicos/para-o-celular/planos-controle | V86: data/raw/vivo_control_SP.html
A87: 2026-06-23 | B87: 2026-06-23T22:10:23 | C87: vivo | D87: control | E87: SP | F87: Vivo Controle Saúde | G87: vivo:VIV202600029301-61gb | H87: 90 | L87: 61 | M87: 20 GB de franquia 31 GB de bônus | T87: Assinatura Vale Saúde Sempre inclusa | U87: https://vivo.com.br/para-voce/produtos-e-servicos/para-o-celular/planos-controle | V87: data/raw/vivo_control_SP.html
A88: 2026-06-23 | B88: 2026-06-23T22:10:23 | C88: vivo | D88: lite | E88: SP | F88: Easy Lite | G88: vivo:VIV202600005312-30gb | H88: 30 | L88: 30 | M88: 30 GB de franquia | T88: Youtube Ilimitado | U88: https://vivo.com.br/para-voce/produtos-e-servicos/para-o-celular/easy-lite | V88: data/raw/vivo_lite_SP.html
A89: 2026-06-23 | B89: 2026-06-23T22:10:23 | C89: vivo | D89: lite | E89: SP | F89: Easy Lite | G89: vivo:VIV202600019134-40gb | H89: 40 | L89: 40 | M89: 40 GB de franquia | T89: Youtube Ilimitado | U89: https://vivo.com.br/para-voce/produtos-e-servicos/para-o-celular/easy-lite | V89: data/raw/vivo_lite_SP.html
A90: 2026-06-23 | B90: 2026-06-23T22:10:23 | C90: vivo | D90: lite | E90: SP | F90: Easy Lite | G90: vivo:VIV202600019132-20gb | H90: 35 | L90: 20 | M90: 20 GB de franquia | T90: Youtube Ilimitado | U90: https://vivo.com.br/para-voce/produtos-e-servicos/para-o-celular/easy-lite | V90: data/raw/vivo_lite_SP.html
A91: 2026-06-23 | B91: 2026-06-23T22:10:23 | C91: vivo | D91: postpaid | E91: SP | F91: Vivo Pós com Amazon | G91: vivo:VIV202600029255-60gb | H91: 150 | L91: 60 | M91: 50 GB de franquia 10 GB de bônus | T91: Assinatura Amazon Prime inclusa | U91: https://vivo.com.br/para-voce/produtos-e-servicos/para-o-celular/planos-pos-pago | V91: data/raw/vivo_postpaid_SP.html
A92: 2026-06-23 | B92: 2026-06-23T22:10:23 | C92: vivo | D92: postpaid | E92: SP | F92: Vivo Pós com Disney+ | G92: vivo:VIV202600022115-60gb | H92: 180 | L92: 60 | M92: 50 GB de franquia 10 GB de bônus | R92: Disney+ | T92: Assinatura Disney+ Padrão inclusa | U92: https://vivo.com.br/para-voce/produtos-e-servicos/para-o-celular/planos-pos-pago | V92: data/raw/vivo_postpaid_SP.html
A93: 2026-06-23 | B93: 2026-06-23T22:10:23 | C93: vivo | D93: postpaid | E93: SP | F93: Vivo Pós com Globoplay | G93: vivo:VIV202600029246-60gb | H93: 165 | L93: 60 | M93: 50 GB de franquia 10 GB de bônus | R93: Globoplay | T93: Assinatura Globoplay inclusa | U93: https://vivo.com.br/para-voce/produtos-e-servicos/para-o-celular/planos-pos-pago | V93: data/raw/vivo_postpaid_SP.html
A94: 2026-06-23 | B94: 2026-06-23T22:10:23 | C94: vivo | D94: postpaid | E94: SP | F94: Vivo Pós com Netflix | G94: vivo:VIV202600029234-60gb | H94: 180 | L94: 60 | M94: 50 GB de franquia 10 GB de bônus | R94: Netflix | T94: Assinatura Netflix Padrão inclusa | U94: https://vivo.com.br/para-voce/produtos-e-servicos/para-o-celular/planos-pos-pago | V94: data/raw/vivo_postpaid_SP.html
A95: 2026-06-23 | B95: 2026-06-23T22:10:23 | C95: vivo | D95: postpaid | E95: SP | F95: Vivo Pós com Premiere | G95: vivo:VIV202600029249-60gb | H95: 180 | L95: 60 | M95: 50 GB de franquia 10 GB de bônus | R95: Premiere | T95: Assinatura Premiere inclusa | U95: https://vivo.com.br/para-voce/produtos-e-servicos/para-o-celular/planos-pos-pago | V95: data/raw/vivo_postpaid_SP.html
A96: 2026-06-23 | B96: 2026-06-23T22:10:23 | C96: vivo | D96: postpaid | E96: SP | F96: Vivo Pós com Spotify | G96: vivo:VIV202600029229-60gb | H96: 165 | L96: 60 | M96: 50 GB de franquia 10 GB de bônus | R96: Spotify | T96: Assinatura Spotify Premium inclusa | U96: https://vivo.com.br/para-voce/produtos-e-servicos/para-o-celular/planos-pos-pago | V96: data/raw/vivo_postpaid_SP.html
A97: 2026-06-23 | B97: 2026-06-23T22:10:23 | C97: vivo | D97: postpaid | E97: SP | F97: Vivo Pós com Travel | G97: vivo:VIV202600029244-70gb | H97: 215 | L97: 70 | M97: 60 GB de franquia 10 GB de bônus | T97: 6 meses grátis de Gemini com AI Plus | U97: https://vivo.com.br/para-voce/produtos-e-servicos/para-o-celular/planos-pos-pago | V97: data/raw/vivo_postpaid_SP.html
A98: 2026-06-23 | B98: 2026-06-23T22:10:23 | C98: vivo | D98: prepaid | E98: SP | F98: Vivo Pré | G98: vivo:VIV202600022379-25gb | H98: 30 | L98: 25 | M98: 15 GB para navegar como quiser 5 GB de bônus 5 GB para navegar no Youtube | U98: https://vivo.com.br/para-voce/produtos-e-servicos/para-o-celular/pre-pago/vivo-pre | V98: data/raw/vivo_prepaid_SP.html
A99: 2026-06-23 | B99: 2026-06-23T22:10:23 | C99: vivo | D99: prepaid | E99: SP | F99: Vivo Pré | G99: vivo:VIV202600022379-9gb | H99: 25 | L99: 9 | M99: 6 GB para navegar como quiser 3 GB para navegar no YouTube | U99: https://vivo.com.br/para-voce/produtos-e-servicos/para-o-celular/pre-pago/vivo-pre | V99: data/raw/vivo_prepaid_SP.html
A100: 2026-06-23 | B100: 2026-06-23T22:10:23 | C100: vivo | D100: prepaid | E100: SP | F100: Vivo Pré | G100: vivo:VIV202600022379-5gb | H100: 20 | L100: 5 | M100: 5 GB para navegar como quiser | U100: https://vivo.com.br/para-voce/produtos-e-servicos/para-o-celular/pre-pago/vivo-pre | V100: data/raw/vivo_prepaid_SP.html
...

Sheet latest
A1: snapshot_date | B1: snapshot_ts | C1: carrier | D1: category | E1: state | F1: plan_name | G1: plan_id | H1: price_brl | I1: price_promo_brl | J1: price_note | K1: payment_method | L1: data_gb | M1: data_note | N1: validity_days | O1: unlimited_apps | P1: voice | Q1: sms | R1: streaming | S1: loyalty_months | T1: extra_benefits | U1: source_url | V1: raw_ref
A2: 2026-07-13 | B2: 2026-07-13T14:56:28 | C2: claro | D2: control | E2: SP | F2: Controle 25GB | G2: claro:plano-controle-25gb | H2: 59.9 | I2: 54.9 | J2: De R$ 59,90 Por: | L2: 25 | O2: WhatsApp | T2: Para uso livre; Para redes sociais e vídeos; Bônus exclusivo; Aproveite na sua franquia; WhatsApp e ligações ilimitadas | U2: https://www.claro.com.br/celular/controle | V2: data/raw/claro_control_SP.json
A3: 2026-07-13 | B3: 2026-07-13T14:56:28 | C3: claro | D3: control | E3: SP | F3: Controle 30GB | G3: claro:plano-controle-30gb | H3: 69.9 | L3: 30 | O3: WhatsApp | T3: Para uso livre; Bônus especial para uso livre; Bônus para redes sociais e apps; Redes sociais e apps; WhatsApp ilimitado | U3: https://www.claro.com.br/celular/controle | V3: data/raw/claro_control_SP.json
A4: 2026-07-13 | B4: 2026-07-13T14:56:28 | C4: claro | D4: control | E4: SP | F4: Controle 30GB | G4: claro:plano-controle-30gb-gaming | H4: 99.9 | L4: 30 | O4: WhatsApp | T4: Para uso livre; Bônus para redes sociais e apps; Bônus uso livre; Redes sociais e apps; WhatsApp ilimitado | U4: https://www.claro.com.br/celular/controle | V4: data/raw/claro_control_SP.json
A5: 2026-07-13 | B5: 2026-07-13T14:56:28 | C5: claro | D5: flex | E5: SP | F5: Flex 15GB | G5: claro:plano-flex-15gb | H5: 44.9 | L5: 15 | O5: WhatsApp | T5: Para uso livre; Bônus especial para uso livre; Para redes sociais e apps; Bônus extra nos apps; WhatsApp ilimitado | U5: https://www.claro.com.br/celular/flex | V5: data/raw/claro_flex_SP.json
A6: 2026-07-13 | B6: 2026-07-13T14:56:28 | C6: claro | D6: flex | E6: SP | F6: Flex 20GB | G6: claro:plano-flex-20gb | H6: 59.9 | L6: 20 | O6: WhatsApp | T6: Para uso livre; Bônus especial para uso livre; Para redes sociais e apps; Bônus extra nos apps; WhatsApp ilimitado | U6: https://www.claro.com.br/celular/flex | V6: data/raw/claro_flex_SP.json
A7: 2026-07-13 | B7: 2026-07-13T14:56:28 | C7: claro | D7: flex | E7: SP | F7: Flex 30GB | G7: claro:plano-flex-30gb | H7: 69.9 | L7: 30 | O7: WhatsApp | T7: Para uso livre; Bônus especial para uso livre; Para redes sociais e apps; Bônus extra nos apps; WhatsApp ilimitado; Assinatura Claro musica inclusa | U7: https://www.claro.com.br/celular/flex | V7: data/raw/claro_flex_SP.json
A8: 2026-07-13 | B8: 2026-07-13T14:56:28 | C8: claro | D8: flex | E8: SP | F8: Flex 40GB | G8: claro:plano-flex-40gb | H8: 119.9 | L8: 40 | O8: WhatsApp | T8: Para uso livre; Para redes sociais e apps; Bônus uso livre; Bônus extra nos apps; WhatsApp ilimitado; Assinatura Claro musica inclusa | U8: https://www.claro.com.br/celular/flex | V8: data/raw/claro_flex_SP.json
A9: 2026-07-13 | B9: 2026-07-13T14:56:28 | C9: claro | D9: postpaid | E9: SP | F9: Pós 100GB | G9: claro:plano-pos-100gb | H9: 179.9 | L9: 100 | O9: WhatsApp | T9: Armazenamento na nuvem:; Google One ou iCloud+; WhatsApp ilimitado; Roaming: Passaporte Américas; Claro Sync: Smartwatch conectado | U9: https://www.claro.com.br/celular/pos | V9: data/raw/claro_postpaid_SP.json
A10: 2026-07-13 | B10: 2026-07-13T14:56:28 | C10: claro | D10: postpaid | E10: SP | F10: Pós 150GB | G10: claro:plano-pos-150gb | H10: 239.9 | L10: 150 | O10: WhatsApp | T10: Armazenamento na nuvem:; Google One ou iCloud+; WhatsApp ilimitado; Roaming: Passaporte Américas e Europa; Claro Sync: Smartwatch conectado | U10: https://www.claro.com.br/celular/pos | V10: data/raw/claro_postpaid_SP.json
A11: 2026-07-13 | B11: 2026-07-13T14:56:28 | C11: claro | D11: postpaid | E11: SP | F11: Pós 200GB | G11: claro:plano-pos-200gb | H11: 339.9 | L11: 200 | O11: WhatsApp | T11: Armazenamento na nuvem:; Google One ou iCloud+; WhatsApp ilimitado; Roaming: Passaporte Mundo; Claro Sync: Smartwatch conectado | U11: https://www.claro.com.br/celular/pos | V11: data/raw/claro_postpaid_SP.json
A12: 2026-07-13 | B12: 2026-07-13T14:56:28 | C12: claro | D12: postpaid | E12: SP | F12: Pós 50GB com GeForce NOW | G12: claro:plano-pos-60gb-geforce | H12: 164.9 | L12: 50 | O12: WhatsApp | T12: Armazenamento na nuvem:; Google One ou iCloud+; WhatsApp ilimitado; Roaming: Passaporte Américas; Claro Sync: Smartwatch conectado; Inclusa assinatura GeForce NOW | U12: https://www.claro.com.br/celular/pos | V12: data/raw/claro_postpaid_SP.json
A13: 2026-07-13 | B13: 2026-07-13T14:56:28 | C13: claro | D13: postpaid | E13: SP | F13: Pós 60GB | G13: claro:plano-pos-60gb | H13: 124.9 | L13: 60 | O13: WhatsApp | T13: Armazenamento na nuvem:; Google One ou iCloud+; WhatsApp ilimitado; Roaming: Passaporte Américas; Claro Sync: Smartwatch conectado | U13: https://www.claro.com.br/celular/pos | V13: data/raw/claro_postpaid_SP.json
A14: 2026-07-13 | B14: 2026-07-13T14:56:28 | C14: claro | D14: prepaid | E14: SP | F14: Prezão 10GB (25 dias) | G14: claro:prezao-25d-10gb | H14: 25 | J14: recarga Prezão R$25 — validade 25 dias | L14: 10 | N14: 25 | U14: https://www.claro.com.br/celular/planos-pre/prezao | V14: data/raw/claro_prepaid_SP.json
A15: 2026-07-13 | B15: 2026-07-13T14:56:28 | C15: claro | D15: prepaid | E15: SP | F15: Prezão 12GB (30 dias) | G15: claro:prezao-30d-12gb | H15: 30 | J15: recarga Prezão R$30 — validade 30 dias | L15: 12 | N15: 30 | U15: https://www.claro.com.br/celular/planos-pre/prezao | V15: data/raw/claro_prepaid_SP.json
A16: 2026-07-13 | B16: 2026-07-13T14:56:28 | C16: claro | D16: prepaid | E16: SP | F16: Prezão 4GB (12 dias) | G16: claro:prezao-12d-4gb | H16: 15 | J16: recarga Prezão R$15 — validade 12 dias | L16: 4 | N16: 12 | U16: https://www.claro.com.br/celular/planos-pre/prezao | V16: data/raw/claro_prepaid_SP.json
A17: 2026-07-13 | B17: 2026-07-13T14:56:28 | C17: claro | D17: prepaid | E17: SP | F17: Prezão 5GB (15 dias) | G17: claro:prezao-15d-5gb | H17: 15 | J17: recarga Prezão R$15 — validade 15 dias | L17: 5 | N17: 15 | U17: https://www.claro.com.br/celular/planos-pre/prezao | V17: data/raw/claro_prepaid_SP.json
A18: 2026-07-13 | B18: 2026-07-13T14:56:28 | C18: claro | D18: prepaid | E18: SP | F18: Prezão 6GB (20 dias) | G18: claro:prezao-20d-6gb | H18: 20 | J18: recarga Prezão R$20 — validade 20 dias | L18: 6 | N18: 20 | U18: https://www.claro.com.br/celular/planos-pre/prezao | V18: data/raw/claro_prepaid_SP.json
A19: 2026-07-13 | B19: 2026-07-13T14:56:28 | C19: claro | D19: prepaid | E19: SP | F19: Prezão 8GB (20 dias) | G19: claro:prezao-20d-8gb | H19: 20 | J19: recarga Prezão R$20 — validade 20 dias | L19: 8 | N19: 20 | U19: https://www.claro.com.br/celular/planos-pre/prezao | V19: data/raw/claro_prepaid_SP.json
A20: 2026-07-13 | B20: 2026-07-13T14:56:28 | C20: claro | D20: prepaid | E20: SP | F20: Prezão 9GB (25 dias) | G20: claro:prezao-25d-9gb | H20: 25 | J20: recarga Prezão R$25 — validade 25 dias | L20: 9 | N20: 25 | U20: https://www.claro.com.br/celular/planos-pre/prezao | V20: data/raw/claro_prepaid_SP.json
A21: 2026-07-13 | B21: 2026-07-13T14:56:28 | C21: tim | D21: control | E21: SP | F21: TIM Controle 41GB | G21: tim:167036 | H21: 49.99 | L21: 41 | U21: https://www.tim.com.br/sp/para-voce/planos/controle | V21: data/raw/tim_control_SP.html
A22: 2026-07-13 | B22: 2026-07-13T14:56:28 | C22: tim | D22: control | E22: SP | F22: TIM Controle Light Express 31GB | G22: tim:167046 | H22: 60.99 | L22: 31 | U22: https://www.tim.com.br/sp/para-voce/planos/controle | V22: data/raw/tim_control_SP.html
A23: 2026-07-13 | B23: 2026-07-13T14:56:28 | C23: tim | D23: control | E23: SP | F23: TIM Controle Plus 45GB | G23: tim:167031 | H23: 59.99 | L23: 45 | U23: https://www.tim.com.br/sp/para-voce/planos/controle | V23: data/raw/tim_control_SP.html
A24: 2026-07-13 | B24: 2026-07-13T14:56:28 | C24: tim | D24: control | E24: SP | F24: TIM Controle Premium 53GB | G24: tim:167041 | H24: 69.99 | L24: 53 | U24: https://www.tim.com.br/sp/para-voce/planos/controle | V24: data/raw/tim_control_SP.html
A25: 2026-07-13 | B25: 2026-07-13T14:56:28 | C25: tim | D25: control | E25: SP | F25: TIM Controle Pro Express | G25: tim:167051 | H25: 64.99 | U25: https://www.tim.com.br/sp/para-voce/planos/controle | V25: data/raw/tim_control_SP.html
A26: 2026-07-13 | B26: 2026-07-13T14:56:28 | C26: tim | D26: fit | E26: SP | F26: TIM Controle Fit Anual | G26: tim:TIM202600000271 | H26: 30 | J26: plano anual 12x no cartão de crédito; prazo de permanência 12m | K26: credit_card | L26: 30 | S26: 12 | U26: https://www.tim.com.br/sp/para-voce/planos/controle | V26: data/raw/tim_fit_SP.html
A27: 2026-07-13 | B27: 2026-07-13T14:56:28 | C27: tim | D27: fit | E27: SP | F27: TIM Controle Fit Mensal | G27: tim:TIM202600000270 | H27: 35 | J27: plano mensal, sem prazo de permanência | L27: 20 | U27: https://www.tim.com.br/sp/para-voce/planos/controle | V27: data/raw/tim_fit_SP.html
A28: 2026-07-13 | B28: 2026-07-13T14:56:28 | C28: tim | D28: postpaid | E28: SP | F28: TIM Black 70GB | G28: tim:54206 | H28: 129.99 | K28: bill | L28: 70 | U28: https://www.tim.com.br/sp/para-voce/planos/pos-pago/tim-black | V28: data/raw/tim_postpaid_SP.html
A29: 2026-07-13 | B29: 2026-07-13T14:56:28 | C29: tim | D29: postpaid | E29: SP | F29: TIM Black A Express 67GB | G29: tim:55121 | H29: 119.99 | K29: credit_card | L29: 67 | U29: https://www.tim.com.br/sp/para-voce/planos/pos-pago/tim-black | V29: data/raw/tim_postpaid_SP.html
A30: 2026-07-13 | B30: 2026-07-13T14:56:28 | C30: tim | D30: postpaid | E30: SP | F30: TIM Black B Express 82GB | G30: tim:52146 | H30: 144.99 | K30: credit_card | L30: 82 | U30: https://www.tim.com.br/sp/para-voce/planos/pos-pago/tim-black | V30: data/raw/tim_postpaid_SP.html
A31: 2026-07-13 | B31: 2026-07-13T14:56:28 | C31: tim | D31: postpaid | E31: SP | F31: TIM Black C Express 107GB | G31: tim:52151 | H31: 164.99 | K31: credit_card | L31: 107 | U31: https://www.tim.com.br/sp/para-voce/planos/pos-pago/tim-black | V31: data/raw/tim_postpaid_SP.html
A32: 2026-07-13 | B32: 2026-07-13T14:56:28 | C32: tim | D32: postpaid | E32: SP | F32: TIM Black C Ultra 95GB | G32: tim:100581 | H32: 159.99 | K32: bill | L32: 95 | U32: https://www.tim.com.br/sp/para-voce/planos/pos-pago/tim-black | V32: data/raw/tim_postpaid_SP.html
A33: 2026-07-13 | B33: 2026-07-13T14:56:28 | C33: tim | D33: postpaid | E33: SP | F33: TIM Black Plus 80GB | G33: tim:54256 | H33: 149.99 | K33: bill | L33: 80 | U33: https://www.tim.com.br/sp/para-voce/planos/pos-pago/tim-black | V33: data/raw/tim_postpaid_SP.html
A34: 2026-07-13 | B34: 2026-07-13T14:56:28 | C34: tim | D34: postpaid | E34: SP | F34: TIM Black Premium 110GB | G34: tim:54261 | H34: 159.99 | K34: bill | L34: 110 | U34: https://www.tim.com.br/sp/para-voce/planos/pos-pago/tim-black | V34: data/raw/tim_postpaid_SP.html
A35: 2026-07-13 | B35: 2026-07-13T14:56:28 | C35: tim | D35: prepaid | E35: SP | F35: TIM Pré XIP Plus 16GB | G35: tim:106306 | H35: 30 | L35: 16 | N35: 30 | U35: https://www.tim.com.br/sp/para-voce/planos/pre-pago | V35: data/raw/tim_prepaid_SP.html
A36: 2026-07-13 | B36: 2026-07-13T14:56:28 | C36: tim | D36: prepaid | E36: SP | F36: TIM Pré XIP Plus 6GB | G36: tim:59906 | H36: 20 | L36: 6 | N36: 17 | U36: https://www.tim.com.br/sp/para-voce/planos/pre-pago | V36: data/raw/tim_prepaid_SP.html
A37: 2026-07-13 | B37: 2026-07-13T14:56:28 | C37: tim | D37: prepaid | E37: SP | F37: TIM Pré XIP Plus 8GB | G37: tim:59901 | H37: 25 | L37: 8 | N37: 22 | U37: https://www.tim.com.br/sp/para-voce/planos/pre-pago | V37: data/raw/tim_prepaid_SP.html
A38: 2026-07-13 | B38: 2026-07-13T14:56:28 | C38: vivo | D38: control | E38: SP | F38: Vivo Controle | G38: vivo:VIV202600029270-46gb | H38: 59 | L38: 46 | M38: 15 GB de franquia 31 GB de bônus | T38: 2 meses de YouTube sem consumo no plano | U38: https://vivo.com.br/para-voce/produtos-e-servicos/para-o-celular/planos-controle | V38: data/raw/vivo_control_SP.html
A39: 2026-07-13 | B39: 2026-07-13T14:56:28 | C39: vivo | D39: control | E39: SP | F39: Vivo Controle | G39: vivo:VIV202600029300-61gb | H39: 80 | L39: 61 | M39: 20 GB de franquia 31 GB de bônus | T39: 2 meses de YouTube sem consumo no plano | U39: https://vivo.com.br/para-voce/produtos-e-servicos/para-o-celular/planos-controle | V39: data/raw/vivo_control_SP.html
A40: 2026-07-13 | B40: 2026-07-13T14:56:28 | C40: vivo | D40: control | E40: SP | F40: Vivo Controle Educação | G40: vivo:VIV202600029273-61gb | H40: 90 | L40: 61 | M40: 20 GB de franquia 31 GB de bônus | T40: Assinatura Vivae inclusa | U40: https://vivo.com.br/para-voce/produtos-e-servicos/para-o-celular/planos-controle | V40: data/raw/vivo_control_SP.html
A41: 2026-07-13 | B41: 2026-07-13T14:56:28 | C41: vivo | D41: control | E41: SP | F41: Vivo Controle Entretenimento | G41: vivo:VIV202600029307-61gb | H41: 110 | L41: 61 | M41: 20 GB de franquia 31 GB de bônus | T41: Assinatura Vivo TV Inicial inclusa | U41: https://vivo.com.br/para-voce/produtos-e-servicos/para-o-celular/planos-controle | V41: data/raw/vivo_control_SP.html
A42: 2026-07-13 | B42: 2026-07-13T14:56:28 | C42: vivo | D42: control | E42: SP | F42: Vivo Controle Música | G42: vivo:VIV202600029313-61gb | H42: 90 | L42: 61 | M42: 20 GB de franquia 31 GB de bônus | T42: Apple Music Individual | U42: https://vivo.com.br/para-voce/produtos-e-servicos/para-o-celular/planos-controle | V42: data/raw/vivo_control_SP.html
A43: 2026-07-13 | B43: 2026-07-13T14:56:28 | C43: vivo | D43: control | E43: SP | F43: Vivo Controle Netflix | G43: vivo:VIV202600029308-61gb | H43: 95 | L43: 61 | M43: 20 GB de franquia 31 GB de bônus | T43: Assinatura Netflix Padrão com anúncios | U43: https://vivo.com.br/para-voce/produtos-e-servicos/para-o-celular/planos-controle | V43: data/raw/vivo_control_SP.html
A44: 2026-07-13 | B44: 2026-07-13T14:56:28 | C44: vivo | D44: control | E44: SP | F44: Vivo Controle Saúde | G44: vivo:VIV202600029301-61gb | H44: 90 | L44: 61 | M44: 20 GB de franquia 31 GB de bônus | T44: Assinatura Vale Saúde Sempre inclusa | U44: https://vivo.com.br/para-voce/produtos-e-servicos/para-o-celular/planos-controle | V44: data/raw/vivo_control_SP.html
A45: 2026-07-13 | B45: 2026-07-13T14:56:28 | C45: vivo | D45: lite | E45: SP | F45: Easy Lite | G45: vivo:VIV202600032594-30gb | H45: 45 | I45: 30 | J45: preço sem fidelidade; fidelidade 12m no promo | L45: 30 | M45: 30 GB de franquia | S45: 12 | T45: 2 meses de YouTube sem consumo no plano | U45: https://vivo.com.br/para-voce/produtos-e-servicos/para-o-celular/easy-lite | V45: data/raw/vivo_lite_SP.html
A46: 2026-07-13 | B46: 2026-07-13T14:56:28 | C46: vivo | D46: lite | E46: SP | F46: Easy Lite | G46: vivo:VIV202600032596-40gb | H46: 55 | I46: 40 | J46: preço sem fidelidade; fidelidade 12m no promo | L46: 40 | M46: 40 GB de franquia | S46: 12 | T46: 2 meses de YouTube sem consumo no plano | U46: https://vivo.com.br/para-voce/produtos-e-servicos/para-o-celular/easy-lite | V46: data/raw/vivo_lite_SP.html
A47: 2026-07-13 | B47: 2026-07-13T14:56:28 | C47: vivo | D47: lite | E47: SP | F47: Easy Lite | G47: vivo:VIV202600032599-20gb | H47: 35 | L47: 20 | M47: 20 GB de franquia | T47: 2 meses de YouTube sem consumo no plano | U47: https://vivo.com.br/para-voce/produtos-e-servicos/para-o-celular/easy-lite | V47: data/raw/vivo_lite_SP.html
A48: 2026-07-13 | B48: 2026-07-13T14:56:28 | C48: vivo | D48: postpaid | E48: SP | F48: Vivo Pós com Amazon | G48: vivo:VIV202600029255-60gb | H48: 150 | L48: 60 | M48: 50 GB de franquia 10 GB de bônus | T48: Assinatura Amazon Prime inclusa | U48: https://vivo.com.br/para-voce/produtos-e-servicos/para-o-celular/planos-pos-pago | V48: data/raw/vivo_postpaid_SP.html
A49: 2026-07-13 | B49: 2026-07-13T14:56:28 | C49: vivo | D49: postpaid | E49: SP | F49: Vivo Pós com Disney+ | G49: vivo:VIV202600022115-60gb | H49: 180 | L49: 60 | M49: 50 GB de franquia 10 GB de bônus | R49: Disney+ | T49: Assinatura Disney+ Padrão inclusa | U49: https://vivo.com.br/para-voce/produtos-e-servicos/para-o-celular/planos-pos-pago | V49: data/raw/vivo_postpaid_SP.html
A50: 2026-07-13 | B50: 2026-07-13T14:56:28 | C50: vivo | D50: postpaid | E50: SP | F50: Vivo Pós com Globoplay | G50: vivo:VIV202600029246-60gb | H50: 165 | L50: 60 | M50: 50 GB de franquia 10 GB de bônus | R50: Globoplay | T50: Assinatura Globoplay inclusa | U50: https://vivo.com.br/para-voce/produtos-e-servicos/para-o-celular/planos-pos-pago | V50: data/raw/vivo_postpaid_SP.html
A51: 2026-07-13 | B51: 2026-07-13T14:56:28 | C51: vivo | D51: postpaid | E51: SP | F51: Vivo Pós com Netflix | G51: vivo:VIV202600029234-60gb | H51: 180 | L51: 60 | M51: 50 GB de franquia 10 GB de bônus | R51: Netflix | T51: Assinatura Netflix Padrão inclusa | U51: https://vivo.com.br/para-voce/produtos-e-servicos/para-o-celular/planos-pos-pago | V51: data/raw/vivo_postpaid_SP.html
A52: 2026-07-13 | B52: 2026-07-13T14:56:28 | C52: vivo | D52: postpaid | E52: SP | F52: Vivo Pós com Premiere | G52: vivo:VIV202600029249-60gb | H52: 180 | L52: 60 | M52: 50 GB de franquia 10 GB de bônus | R52: Premiere | T52: Assinatura Premiere inclusa | U52: https://vivo.com.br/para-voce/produtos-e-servicos/para-o-celular/planos-pos-pago | V52: data/raw/vivo_postpaid_SP.html
A53: 2026-07-13 | B53: 2026-07-13T14:56:28 | C53: vivo | D53: postpaid | E53: SP | F53: Vivo Pós com Spotify | G53: vivo:VIV202600029229-60gb | H53: 165 | L53: 60 | M53: 50 GB de franquia 10 GB de bônus | R53: Spotify | T53: Assinatura Spotify Premium inclusa | U53: https://vivo.com.br/para-voce/produtos-e-servicos/para-o-celular/planos-pos-pago | V53: data/raw/vivo_postpaid_SP.html
A54: 2026-07-13 | B54: 2026-07-13T14:56:28 | C54: vivo | D54: postpaid | E54: SP | F54: Vivo Pós com Travel | G54: vivo:VIV202600029244-70gb | H54: 215 | L54: 70 | M54: 60 GB de franquia 10 GB de bônus | T54: 2 meses de YouTube sem consumo no plano | U54: https://vivo.com.br/para-voce/produtos-e-servicos/para-o-celular/planos-pos-pago | V54: data/raw/vivo_postpaid_SP.html
A55: 2026-07-13 | B55: 2026-07-13T14:56:28 | C55: vivo | D55: prepaid | E55: SP | F55: Vivo Pré | G55: vivo:VIV202600029370-25gb | H55: 30 | L55: 25 | M55: 15 GB para navegar como quiser 5 GB de bônus 5 GB para navegar no Youtube | N55: 30 | U55: https://vivo.com.br/para-voce/produtos-e-servicos/para-o-celular/pre-pago/vivo-pre | V55: data/raw/vivo_prepaid_SP.html
A56: 2026-07-13 | B56: 2026-07-13T14:56:28 | C56: vivo | D56: prepaid | E56: SP | F56: Vivo Pré | G56: vivo:VIV202600029370-9gb | H56: 25 | L56: 9 | M56: 6 GB para navegar como quiser 3 GB para navegar no YouTube | N56: 22 | U56: https://vivo.com.br/para-voce/produtos-e-servicos/para-o-celular/pre-pago/vivo-pre | V56: data/raw/vivo_prepaid_SP.html
A57: 2026-07-13 | B57: 2026-07-13T14:56:28 | C57: vivo | D57: prepaid | E57: SP | F57: Vivo Pré | G57: vivo:VIV202600029370-5gb | H57: 20 | L57: 5 | M57: 5 GB para navegar como quiser | N57: 17 | U57: https://vivo.com.br/para-voce/produtos-e-servicos/para-o-celular/pre-pago/vivo-pre | V57: data/raw/vivo_prepaid_SP.html
A58: 2026-07-13 | B58: 2026-07-13T14:56:28 | C58: vivo | D58: prepaid | E58: SP | F58: Vivo Pré | G58: vivo:VIV202600029370-4gb | H58: 17 | L58: 4 | M58: 4 GB para navegar como quiser | N58: 15 | U58: https://vivo.com.br/para-voce/produtos-e-servicos/para-o-celular/pre-pago/vivo-pre | V58: data/raw/vivo_prepaid_SP.html

Sheet changes
A1: change_type | B1: carrier | C1: category | D1: state | E1: plan_id | F1: plan_name | G1: old_price_brl | H1: new_price_brl | I1: delta_brl
A2: new | B2: tim | C2: fit | D2: SP | E2: tim:TIM202600000270 | F2: TIM Controle Fit Mensal | H2: 35
A3: new | B3: tim | C3: fit | D3: SP | E3: tim:TIM202600000271 | F3: TIM Controle Fit Anual | H3: 30
A4: price_change | B4: vivo | C4: control | D4: SP | E4: vivo:VIV202600029273-61gb | F4: Vivo Controle Educação | G4: 85 | H4: 90 | I4: 5
A5: price_change | B5: vivo | C5: control | D5: SP | E5: vivo:VIV202600029300-61gb | F5: Vivo Controle | G5: 75 | H5: 80 | I5: 5
A6: price_change | B6: vivo | C6: control | D6: SP | E6: vivo:VIV202600029301-61gb | F6: Vivo Controle Saúde | G6: 85 | H6: 90 | I6: 5
A7: price_change | B7: vivo | C7: control | D7: SP | E7: vivo:VIV202600029307-61gb | F7: Vivo Controle Entretenimento | G7: 105 | H7: 110 | I7: 5
A8: price_change | B8: vivo | C8: control | D8: SP | E8: vivo:VIV202600029308-61gb | F8: Vivo Controle Netflix | G8: 90 | H8: 95 | I8: 5
A9: price_change | B9: vivo | C9: control | D9: SP | E9: vivo:VIV202600029313-61gb | F9: Vivo Controle Música | G9: 85 | H9: 90 | I9: 5
A10: price_change | B10: vivo | C10: lite | D10: SP | E10: vivo:VIV202600032594-30gb | F10: Easy Lite | G10: 30 | H10: 45 | I10: 15
A11: price_change | B11: vivo | C11: lite | D11: SP | E11: vivo:VIV202600032596-40gb | F11: Easy Lite | G11: 40 | H11: 55 | I11: 15

Sheet summary
A1: Mobile Price Tracker — Summary
A3: Run timestamp | B3: 2026-07-13T14:56:28
A4: Latest snapshot | B4: 2026-07-13
A5: Plans in latest | B5: 57
A6: Snapshots in history | B6: 22
A8: carrier | B8: # plans | C8: min price | D8: avg price | E8: max price
A9: vivo | B9: =COUNTIF(latest!$C$2:$C$2000,$A$9) -> 21 | C9: =IFERROR(_xlfn.MINIFS(latest!$H$2:$H$2000,latest!$C$2:$C$2000,$A$9),"-") -> 17 | D9: =IFERROR(AVERAGEIFS(latest!$H$2:$H$2000,latest!$C$2:$C$2000,$A$9),"-") -> 98.86 | E9: =IFERROR(_xlfn.MAXIFS(latest!$H$2:$H$2000,latest!$C$2:$C$2000,$A$9),"-") -> 215
A10: claro | B10: =COUNTIF(latest!$C$2:$C$2000,$A$10) -> 19 | C10: =IFERROR(_xlfn.MINIFS(latest!$H$2:$H$2000,latest!$C$2:$C$2000,$A$10),"-") -> 15 | D10: =IFERROR(AVERAGEIFS(latest!$H$2:$H$2000,latest!$C$2:$C$2000,$A$10),"-") -> 90.73 | E10: =IFERROR(_xlfn.MAXIFS(latest!$H$2:$H$2000,latest!$C$2:$C$2000,$A$10),"-") -> 339.9
A11: tim | B11: =COUNTIF(latest!$C$2:$C$2000,$A$11) -> 17 | C11: =IFERROR(_xlfn.MINIFS(latest!$H$2:$H$2000,latest!$C$2:$C$2000,$A$11),"-") -> 20 | D11: =IFERROR(AVERAGEIFS(latest!$H$2:$H$2000,latest!$C$2:$C$2000,$A$11),"-") -> 86.82 | E11: =IFERROR(_xlfn.MAXIFS(latest!$H$2:$H$2000,latest!$C$2:$C$2000,$A$11),"-") -> 164.99

Sheet comparison
A1: Date | B1: Control (R$/mo) | E1: Post (R$/mo) | H1: Pre (R$/mo, 30-day) | K1: Digital (R$/mo)
B2: TIM | C2: Vivo | D2: Claro | E2: TIM | F2: Vivo | G2: Claro | H2: TIM | I2: Vivo | J2: Claro | K2: TIM | L2: Vivo | M2: Claro
A3: 46195 | B3: =IFERROR(IF(_xlfn.MINIFS(history!$H:$H,history!$C:$C,"tim",history!$D:$D,"control",history!$A:$A,YEAR($A3)&"-"&TEXT(MONTH($A3),"00")&"-"&TEXT(DAY($A3),"00"))=0,"",_xlfn.MINIFS(history!$H:$H,history!$C:$C,"tim",history!$D:$D,"control",history!$A:$A,YEAR($A3)&"-"&TEXT(MONTH($A3),"00")&"-"&TEXT(DAY($A3),"00"))),"") -> 58.99 | C3: =IFERROR(IF(_xlfn.MINIFS(history!$H:$H,history!$C:$C,"vivo",history!$D:$D,"control",history!$A:$A,YEAR($A3)&"-"&TEXT(MONTH($A3),"00")&"-"&TEXT(DAY($A3),"00"))=0,"",_xlfn.MINIFS(history!$H:$H,history!$C:$C,"vivo",history!$D:$D,"control",history!$A:$A,YEAR($A3)&"-"&TEXT(MONTH($A3),"00")&"-"&TEXT(DAY($A3),"00"))),"") -> 59 | D3: =IFERROR(IF(_xlfn.MINIFS(history!$H:$H,history!$C:$C,"claro",history!$D:$D,"control",history!$A:$A,YEAR($A3)&"-"&TEXT(MONTH($A3),"00")&"-"&TEXT(DAY($A3),"00"))=0,"",_xlfn.MINIFS(history!$H:$H,history!$C:$C,"claro",history!$D:$D,"control",history!$A:$A,YEAR($A3)&"-"&TEXT(MONTH($A3),"00")&"-"&TEXT(DAY($A3),"00"))),"") -> 59.9 | E3: =IFERROR(IF(_xlfn.MINIFS(history!$H:$H,history!$C:$C,"tim",history!$D:$D,"postpaid",history!$A:$A,YEAR($A3)&"-"&TEXT(MONTH($A3),"00")&"-"&TEXT(DAY($A3),"00"))=0,"",_xlfn.MINIFS(history!$H:$H,history!$C:$C,"tim",history!$D:$D,"postpaid",history!$A:$A,YEAR($A3)&"-"&TEXT(MONTH($A3),"00")&"-"&TEXT(DAY($A3),"00"))),"") -> 119.99 | F3: =IFERROR(IF(_xlfn.MINIFS(history!$H:$H,history!$C:$C,"vivo",history!$D:$D,"postpaid",history!$A:$A,YEAR($A3)&"-"&TEXT(MONTH($A3),"00")&"-"&TEXT(DAY($A3),"00"))=0,"",_xlfn.MINIFS(history!$H:$H,history!$C:$C,"vivo",history!$D:$D,"postpaid",history!$A:$A,YEAR($A3)&"-"&TEXT(MONTH($A3),"00")&"-"&TEXT(DAY($A3),"00"))),"") -> 150 | G3: =IFERROR(IF(_xlfn.MINIFS(history!$H:$H,history!$C:$C,"claro",history!$D:$D,"postpaid",history!$A:$A,YEAR($A3)&"-"&TEXT(MONTH($A3),"00")&"-"&TEXT(DAY($A3),"00"))=0,"",_xlfn.MINIFS(history!$H:$H,history!$C:$C,"claro",history!$D:$D,"postpaid",history!$A:$A,YEAR($A3)&"-"&TEXT(MONTH($A3),"00")&"-"&TEXT(DAY($A3),"00"))),"") -> 124.9 | H3: =IFERROR(IF(_xlfn.MINIFS(history!$H:$H,history!$C:$C,"tim",history!$D:$D,"prepaid",history!$A:$A,YEAR($A3)&"-"&TEXT(MONTH($A3),"00")&"-"&TEXT(DAY($A3),"00"),history!$N:$N,">=28")=0,"",_xlfn.MINIFS(history!$H:$H,history!$C:$C,"tim",history!$D:$D,"prepaid",history!$A:$A,YEAR($A3)&"-"&TEXT(MONTH($A3),"00")&"-"&TEXT(DAY($A3),"00"),history!$N:$N,">=28")),"") | I3: =IFERROR(IF(_xlfn.MINIFS(history!$H:$H,history!$C:$C,"vivo",history!$D:$D,"prepaid",history!$A:$A,YEAR($A3)&"-"&TEXT(MONTH($A3),"00")&"-"&TEXT(DAY($A3),"00"),history!$N:$N,">=28")=0,"",_xlfn.MINIFS(history!$H:$H,history!$C:$C,"vivo",history!$D:$D,"prepaid",history!$A:$A,YEAR($A3)&"-"&TEXT(MONTH($A3),"00")&"-"&TEXT(DAY($A3),"00"),history!$N:$N,">=28")),"") | J3: =IFERROR(IF(_xlfn.MINIFS(history!$H:$H,history!$C:$C,"claro",history!$D:$D,"prepaid",history!$A:$A,YEAR($A3)&"-"&TEXT(MONTH($A3),"00")&"-"&TEXT(DAY($A3),"00"),history!$N:$N,">=28")=0,"",_xlfn.MINIFS(history!$H:$H,history!$C:$C,"claro",history!$D:$D,"prepaid",history!$A:$A,YEAR($A3)&"-"&TEXT(MONTH($A3),"00")&"-"&TEXT(DAY($A3),"00"),history!$N:$N,">=28")),"") | K3: =IFERROR(1/MAX(IFERROR(1/_xlfn.MINIFS(history!$H:$H,history!$C:$C,"tim",history!$D:$D,"lite",history!$A:$A,YEAR($A3)&"-"&TEXT(MONTH($A3),"00")&"-"&TEXT(DAY($A3),"00"),history!$S:$S,">0"),0),IFERROR(1/_xlfn.MINIFS(history!$H:$H,history!$C:$C,"tim",history!$D:$D,"flex",history!$A:$A,YEAR($A3)&"-"&TEXT(MONTH($A3),"00")&"-"&TEXT(DAY($A3),"00")),0),IFERROR(1/_xlfn.MINIFS(history!$H:$H,history!$C:$C,"tim",history!$D:$D,"fit",history!$A:$A,YEAR($A3)&"-"&TEXT(MONTH($A3),"00")&"-"&TEXT(DAY($A3),"00"),history!$S:$S,"="),0)),"") | L3: =IFERROR(1/MAX(IFERROR(1/_xlfn.MINIFS(history!$H:$H,history!$C:$C,"vivo",history!$D:$D,"lite",history!$A:$A,YEAR($A3)&"-"&TEXT(MONTH($A3),"00")&"-"&TEXT(DAY($A3),"00"),history!$S:$S,">0"),0),IFERROR(1/_xlfn.MINIFS(history!$H:$H,history!$C:$C,"vivo",history!$D:$D,"flex",history!$A:$A,YEAR($A3)&"-"&TEXT(MONTH($A3),"00")&"-"&TEXT(DAY($A3),"00")),0),IFERROR(1/_xlfn.MINIFS(history!$H:$H,history!$C:$C,"vivo",history!$D:$D,"fit",history!$A:$A,YEAR($A3)&"-"&TEXT(MONTH($A3),"00")&"-"&TEXT(DAY($A3),"00"),history!$S:$S,"="),0)),"") | M3: =IFERROR(1/MAX(IFERROR(1/_xlfn.MINIFS(history!$H:$H,history!$C:$C,"claro",history!$D:$D,"lite",history!$A:$A,YEAR($A3)&"-"&TEXT(MONTH($A3),"00")&"-"&TEXT(DAY($A3),"00"),history!$S:$S,">0"),0),IFERROR(1/_xlfn.MINIFS(history!$H:$H,history!$C:$C,"claro",history!$D:$D,"flex",history!$A:$A,YEAR($A3)&"-"&TEXT(MONTH($A3),"00")&"-"&TEXT(DAY($A3),"00")),0),IFERROR(1/_xlfn.MINIFS(history!$H:$H,history!$C:$C,"claro",history!$D:$D,"fit",history!$A:$A,YEAR($A3)&"-"&TEXT(MONTH($A3),"00")&"-"&TEXT(DAY($A3),"00"),history!$S:$S,"="),0)),"") -> 44.9
A4: 46196 | B4: =IFERROR(IF(_xlfn.MINIFS(history!$H:$H,history!$C:$C,"tim",history!$D:$D,"control",history!$A:$A,YEAR($A4)&"-"&TEXT(MONTH($A4),"00")&"-"&TEXT(DAY($A4),"00"))=0,"",_xlfn.MINIFS(history!$H:$H,history!$C:$C,"tim",history!$D:$D,"control",history!$A:$A,YEAR($A4)&"-"&TEXT(MONTH($A4),"00")&"-"&TEXT(DAY($A4),"00"))),"") -> 58.99 | C4: =IFERROR(IF(_xlfn.MINIFS(history!$H:$H,history!$C:$C,"vivo",history!$D:$D,"control",history!$A:$A,YEAR($A4)&"-"&TEXT(MONTH($A4),"00")&"-"&TEXT(DAY($A4),"00"))=0,"",_xlfn.MINIFS(history!$H:$H,history!$C:$C,"vivo",history!$D:$D,"control",history!$A:$A,YEAR($A4)&"-"&TEXT(MONTH($A4),"00")&"-"&TEXT(DAY($A4),"00"))),"") -> 59 | D4: =IFERROR(IF(_xlfn.MINIFS(history!$H:$H,history!$C:$C,"claro",history!$D:$D,"control",history!$A:$A,YEAR($A4)&"-"&TEXT(MONTH($A4),"00")&"-"&TEXT(DAY($A4),"00"))=0,"",_xlfn.MINIFS(history!$H:$H,history!$C:$C,"claro",history!$D:$D,"control",history!$A:$A,YEAR($A4)&"-"&TEXT(MONTH($A4),"00")&"-"&TEXT(DAY($A4),"00"))),"") -> 59.9 | E4: =IFERROR(IF(_xlfn.MINIFS(history!$H:$H,history!$C:$C,"tim",history!$D:$D,"postpaid",history!$A:$A,YEAR($A4)&"-"&TEXT(MONTH($A4),"00")&"-"&TEXT(DAY($A4),"00"))=0,"",_xlfn.MINIFS(history!$H:$H,history!$C:$C,"tim",history!$D:$D,"postpaid",history!$A:$A,YEAR($A4)&"-"&TEXT(MONTH($A4),"00")&"-"&TEXT(DAY($A4),"00"))),"") -> 119.99 | F4: =IFERROR(IF(_xlfn.MINIFS(history!$H:$H,history!$C:$C,"vivo",history!$D:$D,"postpaid",history!$A:$A,YEAR($A4)&"-"&TEXT(MONTH($A4),"00")&"-"&TEXT(DAY($A4),"00"))=0,"",_xlfn.MINIFS(history!$H:$H,history!$C:$C,"vivo",history!$D:$D,"postpaid",history!$A:$A,YEAR($A4)&"-"&TEXT(MONTH($A4),"00")&"-"&TEXT(DAY($A4),"00"))),"") -> 150 | G4: =IFERROR(IF(_xlfn.MINIFS(history!$H:$H,history!$C:$C,"claro",history!$D:$D,"postpaid",history!$A:$A,YEAR($A4)&"-"&TEXT(MONTH($A4),"00")&"-"&TEXT(DAY($A4),"00"))=0,"",_xlfn.MINIFS(history!$H:$H,history!$C:$C,"claro",history!$D:$D,"postpaid",history!$A:$A,YEAR($A4)&"-"&TEXT(MONTH($A4),"00")&"-"&TEXT(DAY($A4),"00"))),"") -> 124.9 | H4: =IFERROR(IF(_xlfn.MINIFS(history!$H:$H,history!$C:$C,"tim",history!$D:$D,"prepaid",history!$A:$A,YEAR($A4)&"-"&TEXT(MONTH($A4),"00")&"-"&TEXT(DAY($A4),"00"),history!$N:$N,">=28")=0,"",_xlfn.MINIFS(history!$H:$H,history!$C:$C,"tim",history!$D:$D,"prepaid",history!$A:$A,YEAR($A4)&"-"&TEXT(MONTH($A4),"00")&"-"&TEXT(DAY($A4),"00"),history!$N:$N,">=28")),"") | I4: =IFERROR(IF(_xlfn.MINIFS(history!$H:$H,history!$C:$C,"vivo",history!$D:$D,"prepaid",history!$A:$A,YEAR($A4)&"-"&TEXT(MONTH($A4),"00")&"-"&TEXT(DAY($A4),"00"),history!$N:$N,">=28")=0,"",_xlfn.MINIFS(history!$H:$H,history!$C:$C,"vivo",history!$D:$D,"prepaid",history!$A:$A,YEAR($A4)&"-"&TEXT(MONTH($A4),"00")&"-"&TEXT(DAY($A4),"00"),history!$N:$N,">=28")),"") | J4: =IFERROR(IF(_xlfn.MINIFS(history!$H:$H,history!$C:$C,"claro",history!$D:$D,"prepaid",history!$A:$A,YEAR($A4)&"-"&TEXT(MONTH($A4),"00")&"-"&TEXT(DAY($A4),"00"),history!$N:$N,">=28")=0,"",_xlfn.MINIFS(history!$H:$H,history!$C:$C,"claro",history!$D:$D,"prepaid",history!$A:$A,YEAR($A4)&"-"&TEXT(MONTH($A4),"00")&"-"&TEXT(DAY($A4),"00"),history!$N:$N,">=28")),"") | K4: =IFERROR(1/MAX(IFERROR(1/_xlfn.MINIFS(history!$H:$H,history!$C:$C,"tim",history!$D:$D,"lite",history!$A:$A,YEAR($A4)&"-"&TEXT(MONTH($A4),"00")&"-"&TEXT(DAY($A4),"00"),history!$S:$S,">0"),0),IFERROR(1/_xlfn.MINIFS(history!$H:$H,history!$C:$C,"tim",history!$D:$D,"flex",history!$A:$A,YEAR($A4)&"-"&TEXT(MONTH($A4),"00")&"-"&TEXT(DAY($A4),"00")),0),IFERROR(1/_xlfn.MINIFS(history!$H:$H,history!$C:$C,"tim",history!$D:$D,"fit",history!$A:$A,YEAR($A4)&"-"&TEXT(MONTH($A4),"00")&"-"&TEXT(DAY($A4),"00"),history!$S:$S,"="),0)),"") | L4: =IFERROR(1/MAX(IFERROR(1/_xlfn.MINIFS(history!$H:$H,history!$C:$C,"vivo",history!$D:$D,"lite",history!$A:$A,YEAR($A4)&"-"&TEXT(MONTH($A4),"00")&"-"&TEXT(DAY($A4),"00"),history!$S:$S,">0"),0),IFERROR(1/_xlfn.MINIFS(history!$H:$H,history!$C:$C,"vivo",history!$D:$D,"flex",history!$A:$A,YEAR($A4)&"-"&TEXT(MONTH($A4),"00")&"-"&TEXT(DAY($A4),"00")),0),IFERROR(1/_xlfn.MINIFS(history!$H:$H,history!$C:$C,"vivo",history!$D:$D,"fit",history!$A:$A,YEAR($A4)&"-"&TEXT(MONTH($A4),"00")&"-"&TEXT(DAY($A4),"00"),history!$S:$S,"="),0)),"") | M4: =IFERROR(1/MAX(IFERROR(1/_xlfn.MINIFS(history!$H:$H,history!$C:$C,"claro",history!$D:$D,"lite",history!$A:$A,YEAR($A4)&"-"&TEXT(MONTH($A4),"00")&"-"&TEXT(DAY($A4),"00"),history!$S:$S,">0"),0),IFERROR(1/_xlfn.MINIFS(history!$H:$H,history!$C:$C,"claro",history!$D:$D,"flex",history!$A:$A,YEAR($A4)&"-"&TEXT(MONTH($A4),"00")&"-"&TEXT(DAY($A4),"00")),0),IFERROR(1/_xlfn.MINIFS(history!$H:$H,history!$C:$C,"claro",history!$D:$D,"fit",history!$A:$A,YEAR($A4)&"-"&TEXT(MONTH($A4),"00")&"-"&TEXT(DAY($A4),"00"),history!$S:$S,"="),0)),"") -> 44.9
A5: 46197 | B5: =IFERROR(IF(_xlfn.MINIFS(history!$H:$H,history!$C:$C,"tim",history!$D:$D,"control",history!$A:$A,YEAR($A5)&"-"&TEXT(MONTH($A5),"00")&"-"&TEXT(DAY($A5),"00"))=0,"",_xlfn.MINIFS(history!$H:$H,history!$C:$C,"tim",history!$D:$D,"control",history!$A:$A,YEAR($A5)&"-"&TEXT(MONTH($A5),"00")&"-"&TEXT(DAY($A5),"00"))),"") -> 58.99 | C5: =IFERROR(IF(_xlfn.MINIFS(history!$H:$H,history!$C:$C,"vivo",history!$D:$D,"control",history!$A:$A,YEAR($A5)&"-"&TEXT(MONTH($A5),"00")&"-"&TEXT(DAY($A5),"00"))=0,"",_xlfn.MINIFS(history!$H:$H,history!$C:$C,"vivo",history!$D:$D,"control",history!$A:$A,YEAR($A5)&"-"&TEXT(MONTH($A5),"00")&"-"&TEXT(DAY($A5),"00"))),"") -> 59 | D5: =IFERROR(IF(_xlfn.MINIFS(history!$H:$H,history!$C:$C,"claro",history!$D:$D,"control",history!$A:$A,YEAR($A5)&"-"&TEXT(MONTH($A5),"00")&"-"&TEXT(DAY($A5),"00"))=0,"",_xlfn.MINIFS(history!$H:$H,history!$C:$C,"claro",history!$D:$D,"control",history!$A:$A,YEAR($A5)&"-"&TEXT(MONTH($A5),"00")&"-"&TEXT(DAY($A5),"00"))),"") -> 59.9 | E5: =IFERROR(IF(_xlfn.MINIFS(history!$H:$H,history!$C:$C,"tim",history!$D:$D,"postpaid",history!$A:$A,YEAR($A5)&"-"&TEXT(MONTH($A5),"00")&"-"&TEXT(DAY($A5),"00"))=0,"",_xlfn.MINIFS(history!$H:$H,history!$C:$C,"tim",history!$D:$D,"postpaid",history!$A:$A,YEAR($A5)&"-"&TEXT(MONTH($A5),"00")&"-"&TEXT(DAY($A5),"00"))),"") -> 119.99 | F5: =IFERROR(IF(_xlfn.MINIFS(history!$H:$H,history!$C:$C,"vivo",history!$D:$D,"postpaid",history!$A:$A,YEAR($A5)&"-"&TEXT(MONTH($A5),"00")&"-"&TEXT(DAY($A5),"00"))=0,"",_xlfn.MINIFS(history!$H:$H,history!$C:$C,"vivo",history!$D:$D,"postpaid",history!$A:$A,YEAR($A5)&"-"&TEXT(MONTH($A5),"00")&"-"&TEXT(DAY($A5),"00"))),"") -> 150 | G5: =IFERROR(IF(_xlfn.MINIFS(history!$H:$H,history!$C:$C,"claro",history!$D:$D,"postpaid",history!$A:$A,YEAR($A5)&"-"&TEXT(MONTH($A5),"00")&"-"&TEXT(DAY($A5),"00"))=0,"",_xlfn.MINIFS(history!$H:$H,history!$C:$C,"claro",history!$D:$D,"postpaid",history!$A:$A,YEAR($A5)&"-"&TEXT(MONTH($A5),"00")&"-"&TEXT(DAY($A5),"00"))),"") -> 124.9 | H5: =IFERROR(IF(_xlfn.MINIFS(history!$H:$H,history!$C:$C,"tim",history!$D:$D,"prepaid",history!$A:$A,YEAR($A5)&"-"&TEXT(MONTH($A5),"00")&"-"&TEXT(DAY($A5),"00"),history!$N:$N,">=28")=0,"",_xlfn.MINIFS(history!$H:$H,history!$C:$C,"tim",history!$D:$D,"prepaid",history!$A:$A,YEAR($A5)&"-"&TEXT(MONTH($A5),"00")&"-"&TEXT(DAY($A5),"00"),history!$N:$N,">=28")),"") | I5: =IFERROR(IF(_xlfn.MINIFS(history!$H:$H,history!$C:$C,"vivo",history!$D:$D,"prepaid",history!$A:$A,YEAR($A5)&"-"&TEXT(MONTH($A5),"00")&"-"&TEXT(DAY($A5),"00"),history!$N:$N,">=28")=0,"",_xlfn.MINIFS(history!$H:$H,history!$C:$C,"vivo",history!$D:$D,"prepaid",history!$A:$A,YEAR($A5)&"-"&TEXT(MONTH($A5),"00")&"-"&TEXT(DAY($A5),"00"),history!$N:$N,">=28")),"") | J5: =IFERROR(IF(_xlfn.MINIFS(history!$H:$H,history!$C:$C,"claro",history!$D:$D,"prepaid",history!$A:$A,YEAR($A5)&"-"&TEXT(MONTH($A5),"00")&"-"&TEXT(DAY($A5),"00"),history!$N:$N,">=28")=0,"",_xlfn.MINIFS(history!$H:$H,history!$C:$C,"claro",history!$D:$D,"prepaid",history!$A:$A,YEAR($A5)&"-"&TEXT(MONTH($A5),"00")&"-"&TEXT(DAY($A5),"00"),history!$N:$N,">=28")),"") | K5: =IFERROR(1/MAX(IFERROR(1/_xlfn.MINIFS(history!$H:$H,history!$C:$C,"tim",history!$D:$D,"lite",history!$A:$A,YEAR($A5)&"-"&TEXT(MONTH($A5),"00")&"-"&TEXT(DAY($A5),"00"),history!$S:$S,">0"),0),IFERROR(1/_xlfn.MINIFS(history!$H:$H,history!$C:$C,"tim",history!$D:$D,"flex",history!$A:$A,YEAR($A5)&"-"&TEXT(MONTH($A5),"00")&"-"&TEXT(DAY($A5),"00")),0),IFERROR(1/_xlfn.MINIFS(history!$H:$H,history!$C:$C,"tim",history!$D:$D,"fit",history!$A:$A,YEAR($A5)&"-"&TEXT(MONTH($A5),"00")&"-"&TEXT(DAY($A5),"00"),history!$S:$S,"="),0)),"") | L5: =IFERROR(1/MAX(IFERROR(1/_xlfn.MINIFS(history!$H:$H,history!$C:$C,"vivo",history!$D:$D,"lite",history!$A:$A,YEAR($A5)&"-"&TEXT(MONTH($A5),"00")&"-"&TEXT(DAY($A5),"00"),history!$S:$S,">0"),0),IFERROR(1/_xlfn.MINIFS(history!$H:$H,history!$C:$C,"vivo",history!$D:$D,"flex",history!$A:$A,YEAR($A5)&"-"&TEXT(MONTH($A5),"00")&"-"&TEXT(DAY($A5),"00")),0),IFERROR(1/_xlfn.MINIFS(history!$H:$H,history!$C:$C,"vivo",history!$D:$D,"fit",history!$A:$A,YEAR($A5)&"-"&TEXT(MONTH($A5),"00")&"-"&TEXT(DAY($A5),"00"),history!$S:$S,"="),0)),"") | M5: =IFERROR(1/MAX(IFERROR(1/_xlfn.MINIFS(history!$H:$H,history!$C:$C,"claro",history!$D:$D,"lite",history!$A:$A,YEAR($A5)&"-"&TEXT(MONTH($A5),"00")&"-"&TEXT(DAY($A5),"00"),history!$S:$S,">0"),0),IFERROR(1/_xlfn.MINIFS(history!$H:$H,history!$C:$C,"claro",history!$D:$D,"flex",history!$A:$A,YEAR($A5)&"-"&TEXT(MONTH($A5),"00")&"-"&TEXT(DAY($A5),"00")),0),IFERROR(1/_xlfn.MINIFS(history!$H:$H,history!$C:$C,"claro",history!$D:$D,"fit",history!$A:$A,YEAR($A5)&"-"&TEXT(MONTH($A5),"00")&"-"&TEXT(DAY($A5),"00"),history!$S:$S,"="),0)),"") -> 44.9
A6: 46198 | B6: =IFERROR(IF(_xlfn.MINIFS(history!$H:$H,history!$C:$C,"tim",history!$D:$D,"control",history!$A:$A,YEAR($A6)&"-"&TEXT(MONTH($A6),"00")&"-"&TEXT(DAY($A6),"00"))=0,"",_xlfn.MINIFS(history!$H:$H,history!$C:$C,"tim",history!$D:$D,"control",history!$A:$A,YEAR($A6)&"-"&TEXT(MONTH($A6),"00")&"-"&TEXT(DAY($A6),"00"))),"") -> 58.99 | C6: =IFERROR(IF(_xlfn.MINIFS(history!$H:$H,history!$C:$C,"vivo",history!$D:$D,"control",history!$A:$A,YEAR($A6)&"-"&TEXT(MONTH($A6),"00")&"-"&TEXT(DAY($A6),"00"))=0,"",_xlfn.MINIFS(history!$H:$H,history!$C:$C,"vivo",history!$D:$D,"control",history!$A:$A,YEAR($A6)&"-"&TEXT(MONTH($A6),"00")&"-"&TEXT(DAY($A6),"00"))),"") -> 59 | D6: =IFERROR(IF(_xlfn.MINIFS(history!$H:$H,history!$C:$C,"claro",history!$D:$D,"control",history!$A:$A,YEAR($A6)&"-"&TEXT(MONTH($A6),"00")&"-"&TEXT(DAY($A6),"00"))=0,"",_xlfn.MINIFS(history!$H:$H,history!$C:$C,"claro",history!$D:$D,"control",history!$A:$A,YEAR($A6)&"-"&TEXT(MONTH($A6),"00")&"-"&TEXT(DAY($A6),"00"))),"") -> 59.9 | E6: =IFERROR(IF(_xlfn.MINIFS(history!$H:$H,history!$C:$C,"tim",history!$D:$D,"postpaid",history!$A:$A,YEAR($A6)&"-"&TEXT(MONTH($A6),"00")&"-"&TEXT(DAY($A6),"00"))=0,"",_xlfn.MINIFS(history!$H:$H,history!$C:$C,"tim",history!$D:$D,"postpaid",history!$A:$A,YEAR($A6)&"-"&TEXT(MONTH($A6),"00")&"-"&TEXT(DAY($A6),"00"))),"") -> 119.99 | F6: =IFERROR(IF(_xlfn.MINIFS(history!$H:$H,history!$C:$C,"vivo",history!$D:$D,"postpaid",history!$A:$A,YEAR($A6)&"-"&TEXT(MONTH($A6),"00")&"-"&TEXT(DAY($A6),"00"))=0,"",_xlfn.MINIFS(history!$H:$H,history!$C:$C,"vivo",history!$D:$D,"postpaid",history!$A:$A,YEAR($A6)&"-"&TEXT(MONTH($A6),"00")&"-"&TEXT(DAY($A6),"00"))),"") -> 150 | G6: =IFERROR(IF(_xlfn.MINIFS(history!$H:$H,history!$C:$C,"claro",history!$D:$D,"postpaid",history!$A:$A,YEAR($A6)&"-"&TEXT(MONTH($A6),"00")&"-"&TEXT(DAY($A6),"00"))=0,"",_xlfn.MINIFS(history!$H:$H,history!$C:$C,"claro",history!$D:$D,"postpaid",history!$A:$A,YEAR($A6)&"-"&TEXT(MONTH($A6),"00")&"-"&TEXT(DAY($A6),"00"))),"") -> 124.9 | H6: =IFERROR(IF(_xlfn.MINIFS(history!$H:$H,history!$C:$C,"tim",history!$D:$D,"prepaid",history!$A:$A,YEAR($A6)&"-"&TEXT(MONTH($A6),"00")&"-"&TEXT(DAY($A6),"00"),history!$N:$N,">=28")=0,"",_xlfn.MINIFS(history!$H:$H,history!$C:$C,"tim",history!$D:$D,"prepaid",history!$A:$A,YEAR($A6)&"-"&TEXT(MONTH($A6),"00")&"-"&TEXT(DAY($A6),"00"),history!$N:$N,">=28")),"") | I6: =IFERROR(IF(_xlfn.MINIFS(history!$H:$H,history!$C:$C,"vivo",history!$D:$D,"prepaid",history!$A:$A,YEAR($A6)&"-"&TEXT(MONTH($A6),"00")&"-"&TEXT(DAY($A6),"00"),history!$N:$N,">=28")=0,"",_xlfn.MINIFS(history!$H:$H,history!$C:$C,"vivo",history!$D:$D,"prepaid",history!$A:$A,YEAR($A6)&"-"&TEXT(MONTH($A6),"00")&"-"&TEXT(DAY($A6),"00"),history!$N:$N,">=28")),"") | J6: =IFERROR(IF(_xlfn.MINIFS(history!$H:$H,history!$C:$C,"claro",history!$D:$D,"prepaid",history!$A:$A,YEAR($A6)&"-"&TEXT(MONTH($A6),"00")&"-"&TEXT(DAY($A6),"00"),history!$N:$N,">=28")=0,"",_xlfn.MINIFS(history!$H:$H,history!$C:$C,"claro",history!$D:$D,"prepaid",history!$A:$A,YEAR($A6)&"-"&TEXT(MONTH($A6),"00")&"-"&TEXT(DAY($A6),"00"),history!$N:$N,">=28")),"") | K6: =IFERROR(1/MAX(IFERROR(1/_xlfn.MINIFS(history!$H:$H,history!$C:$C,"tim",history!$D:$D,"lite",history!$A:$A,YEAR($A6)&"-"&TEXT(MONTH($A6),"00")&"-"&TEXT(DAY($A6),"00"),history!$S:$S,">0"),0),IFERROR(1/_xlfn.MINIFS(history!$H:$H,history!$C:$C,"tim",history!$D:$D,"flex",history!$A:$A,YEAR($A6)&"-"&TEXT(MONTH($A6),"00")&"-"&TEXT(DAY($A6),"00")),0),IFERROR(1/_xlfn.MINIFS(history!$H:$H,history!$C:$C,"tim",history!$D:$D,"fit",history!$A:$A,YEAR($A6)&"-"&TEXT(MONTH($A6),"00")&"-"&TEXT(DAY($A6),"00"),history!$S:$S,"="),0)),"") | L6: =IFERROR(1/MAX(IFERROR(1/_xlfn.MINIFS(history!$H:$H,history!$C:$C,"vivo",history!$D:$D,"lite",history!$A:$A,YEAR($A6)&"-"&TEXT(MONTH($A6),"00")&"-"&TEXT(DAY($A6),"00"),history!$S:$S,">0"),0),IFERROR(1/_xlfn.MINIFS(history!$H:$H,history!$C:$C,"vivo",history!$D:$D,"flex",history!$A:$A,YEAR($A6)&"-"&TEXT(MONTH($A6),"00")&"-"&TEXT(DAY($A6),"00")),0),IFERROR(1/_xlfn.MINIFS(history!$H:$H,history!$C:$C,"vivo",history!$D:$D,"fit",history!$A:$A,YEAR($A6)&"-"&TEXT(MONTH($A6),"00")&"-"&TEXT(DAY($A6),"00"),history!$S:$S,"="),0)),"") | M6: =IFERROR(1/MAX(IFERROR(1/_xlfn.MINIFS(history!$H:$H,history!$C:$C,"claro",history!$D:$D,"lite",history!$A:$A,YEAR($A6)&"-"&TEXT(MONTH($A6),"00")&"-"&TEXT(DAY($A6),"00"),history!$S:$S,">0"),0),IFERROR(1/_xlfn.MINIFS(history!$H:$H,history!$C:$C,"claro",history!$D:$D,"flex",history!$A:$A,YEAR($A6)&"-"&TEXT(MONTH($A6),"00")&"-"&TEXT(DAY($A6),"00")),0),IFERROR(1/_xlfn.MINIFS(history!$H:$H,history!$C:$C,"claro",history!$D:$D,"fit",history!$A:$A,YEAR($A6)&"-"&TEXT(MONTH($A6),"00")&"-"&TEXT(DAY($A6),"00"),history!$S:$S,"="),0)),"") -> 44.9
A7: 46199 | B7: =IFERROR(IF(_xlfn.MINIFS(history!$H:$H,history!$C:$C,"tim",history!$D:$D,"control",history!$A:$A,YEAR($A7)&"-"&TEXT(MONTH($A7),"00")&"-"&TEXT(DAY($A7),"00"))=0,"",_xlfn.MINIFS(history!$H:$H,history!$C:$C,"tim",history!$D:$D,"control",history!$A:$A,YEAR($A7)&"-"&TEXT(MONTH($A7),"00")&"-"&TEXT(DAY($A7),"00"))),"") -> 58.99 | C7: =IFERROR(IF(_xlfn.MINIFS(history!$H:$H,history!$C:$C,"vivo",history!$D:$D,"control",history!$A:$A,YEAR($A7)&"-"&TEXT(MONTH($A7),"00")&"-"&TEXT(DAY($A7),"00"))=0,"",_xlfn.MINIFS(history!$H:$H,history!$C:$C,"vivo",history!$D:$D,"control",history!$A:$A,YEAR($A7)&"-"&TEXT(MONTH($A7),"00")&"-"&TEXT(DAY($A7),"00"))),"") -> 59 | D7: =IFERROR(IF(_xlfn.MINIFS(history!$H:$H,history!$C:$C,"claro",history!$D:$D,"control",history!$A:$A,YEAR($A7)&"-"&TEXT(MONTH($A7),"00")&"-"&TEXT(DAY($A7),"00"))=0,"",_xlfn.MINIFS(history!$H:$H,history!$C:$C,"claro",history!$D:$D,"control",history!$A:$A,YEAR($A7)&"-"&TEXT(MONTH($A7),"00")&"-"&TEXT(DAY($A7),"00"))),"") -> 59.9 | E7: =IFERROR(IF(_xlfn.MINIFS(history!$H:$H,history!$C:$C,"tim",history!$D:$D,"postpaid",history!$A:$A,YEAR($A7)&"-"&TEXT(MONTH($A7),"00")&"-"&TEXT(DAY($A7),"00"))=0,"",_xlfn.MINIFS(history!$H:$H,history!$C:$C,"tim",history!$D:$D,"postpaid",history!$A:$A,YEAR($A7)&"-"&TEXT(MONTH($A7),"00")&"-"&TEXT(DAY($A7),"00"))),"") -> 119.99 | F7: =IFERROR(IF(_xlfn.MINIFS(history!$H:$H,history!$C:$C,"vivo",history!$D:$D,"postpaid",history!$A:$A,YEAR($A7)&"-"&TEXT(MONTH($A7),"00")&"-"&TEXT(DAY($A7),"00"))=0,"",_xlfn.MINIFS(history!$H:$H,history!$C:$C,"vivo",history!$D:$D,"postpaid",history!$A:$A,YEAR($A7)&"-"&TEXT(MONTH($A7),"00")&"-"&TEXT(DAY($A7),"00"))),"") -> 150 | G7: =IFERROR(IF(_xlfn.MINIFS(history!$H:$H,history!$C:$C,"claro",history!$D:$D,"postpaid",history!$A:$A,YEAR($A7)&"-"&TEXT(MONTH($A7),"00")&"-"&TEXT(DAY($A7),"00"))=0,"",_xlfn.MINIFS(history!$H:$H,history!$C:$C,"claro",history!$D:$D,"postpaid",history!$A:$A,YEAR($A7)&"-"&TEXT(MONTH($A7),"00")&"-"&TEXT(DAY($A7),"00"))),"") -> 124.9 | H7: =IFERROR(IF(_xlfn.MINIFS(history!$H:$H,history!$C:$C,"tim",history!$D:$D,"prepaid",history!$A:$A,YEAR($A7)&"-"&TEXT(MONTH($A7),"00")&"-"&TEXT(DAY($A7),"00"),history!$N:$N,">=28")=0,"",_xlfn.MINIFS(history!$H:$H,history!$C:$C,"tim",history!$D:$D,"prepaid",history!$A:$A,YEAR($A7)&"-"&TEXT(MONTH($A7),"00")&"-"&TEXT(DAY($A7),"00"),history!$N:$N,">=28")),"") -> 20 | I7: =IFERROR(IF(_xlfn.MINIFS(history!$H:$H,history!$C:$C,"vivo",history!$D:$D,"prepaid",history!$A:$A,YEAR($A7)&"-"&TEXT(MONTH($A7),"00")&"-"&TEXT(DAY($A7),"00"),history!$N:$N,">=28")=0,"",_xlfn.MINIFS(history!$H:$H,history!$C:$C,"vivo",history!$D:$D,"prepaid",history!$A:$A,YEAR($A7)&"-"&TEXT(MONTH($A7),"00")&"-"&TEXT(DAY($A7),"00"),history!$N:$N,">=28")),"") -> 30 | J7: =IFERROR(IF(_xlfn.MINIFS(history!$H:$H,history!$C:$C,"claro",history!$D:$D,"prepaid",history!$A:$A,YEAR($A7)&"-"&TEXT(MONTH($A7),"00")&"-"&TEXT(DAY($A7),"00"),history!$N:$N,">=28")=0,"",_xlfn.MINIFS(history!$H:$H,history!$C:$C,"claro",history!$D:$D,"prepaid",history!$A:$A,YEAR($A7)&"-"&TEXT(MONTH($A7),"00")&"-"&TEXT(DAY($A7),"00"),history!$N:$N,">=28")),"") -> 30 | K7: =IFERROR(1/MAX(IFERROR(1/_xlfn.MINIFS(history!$H:$H,history!$C:$C,"tim",history!$D:$D,"lite",history!$A:$A,YEAR($A7)&"-"&TEXT(MONTH($A7),"00")&"-"&TEXT(DAY($A7),"00"),history!$S:$S,">0"),0),IFERROR(1/_xlfn.MINIFS(history!$H:$H,history!$C:$C,"tim",history!$D:$D,"flex",history!$A:$A,YEAR($A7)&"-"&TEXT(MONTH($A7),"00")&"-"&TEXT(DAY($A7),"00")),0),IFERROR(1/_xlfn.MINIFS(history!$H:$H,history!$C:$C,"tim",history!$D:$D,"fit",history!$A:$A,YEAR($A7)&"-"&TEXT(MONTH($A7),"00")&"-"&TEXT(DAY($A7),"00"),history!$S:$S,"="),0)),"") | L7: =IFERROR(1/MAX(IFERROR(1/_xlfn.MINIFS(history!$H:$H,history!$C:$C,"vivo",history!$D:$D,"lite",history!$A:$A,YEAR($A7)&"-"&TEXT(MONTH($A7),"00")&"-"&TEXT(DAY($A7),"00"),history!$S:$S,">0"),0),IFERROR(1/_xlfn.MINIFS(history!$H:$H,history!$C:$C,"vivo",history!$D:$D,"flex",history!$A:$A,YEAR($A7)&"-"&TEXT(MONTH($A7),"00")&"-"&TEXT(DAY($A7),"00")),0),IFERROR(1/_xlfn.MINIFS(history!$H:$H,history!$C:$C,"vivo",history!$D:$D,"fit",history!$A:$A,YEAR($A7)&"-"&TEXT(MONTH($A7),"00")&"-"&TEXT(DAY($A7),"00"),history!$S:$S,"="),0)),"") | M7: =IFERROR(1/MAX(IFERROR(1/_xlfn.MINIFS(history!$H:$H,history!$C:$C,"claro",history!$D:$D,"lite",history!$A:$A,YEAR($A7)&"-"&TEXT(MONTH($A7),"00")&"-"&TEXT(DAY($A7),"00"),history!$S:$S,">0"),0),IFERROR(1/_xlfn.MINIFS(history!$H:$H,history!$C:$C,"claro",history!$D:$D,"flex",history!$A:$A,YEAR($A7)&"-"&TEXT(MONTH($A7),"00")&"-"&TEXT(DAY($A7),"00")),0),IFERROR(1/_xlfn.MINIFS(history!$H:$H,history!$C:$C,"claro",history!$D:$D,"fit",history!$A:$A,YEAR($A7)&"-"&TEXT(MONTH($A7),"00")&"-"&TEXT(DAY($A7),"00"),history!$S:$S,"="),0)),"") -> 44.9
A8: 46200 | B8: =IFERROR(IF(_xlfn.MINIFS(history!$H:$H,history!$C:$C,"tim",history!$D:$D,"control",history!$A:$A,YEAR($A8)&"-"&TEXT(MONTH($A8),"00")&"-"&TEXT(DAY($A8),"00"))=0,"",_xlfn.MINIFS(history!$H:$H,history!$C:$C,"tim",history!$D:$D,"control",history!$A:$A,YEAR($A8)&"-"&TEXT(MONTH($A8),"00")&"-"&TEXT(DAY($A8),"00"))),"") -> 58.99 | C8: =IFERROR(IF(_xlfn.MINIFS(history!$H:$H,history!$C:$C,"vivo",history!$D:$D,"control",history!$A:$A,YEAR($A8)&"-"&TEXT(MONTH($A8),"00")&"-"&TEXT(DAY($A8),"00"))=0,"",_xlfn.MINIFS(history!$H:$H,history!$C:$C,"vivo",history!$D:$D,"control",history!$A:$A,YEAR($A8)&"-"&TEXT(MONTH($A8),"00")&"-"&TEXT(DAY($A8),"00"))),"") -> 59 | D8: =IFERROR(IF(_xlfn.MINIFS(history!$H:$H,history!$C:$C,"claro",history!$D:$D,"control",history!$A:$A,YEAR($A8)&"-"&TEXT(MONTH($A8),"00")&"-"&TEXT(DAY($A8),"00"))=0,"",_xlfn.MINIFS(history!$H:$H,history!$C:$C,"claro",history!$D:$D,"control",history!$A:$A,YEAR($A8)&"-"&TEXT(MONTH($A8),"00")&"-"&TEXT(DAY($A8),"00"))),"") -> 59.9 | E8: =IFERROR(IF(_xlfn.MINIFS(history!$H:$H,history!$C:$C,"tim",history!$D:$D,"postpaid",history!$A:$A,YEAR($A8)&"-"&TEXT(MONTH($A8),"00")&"-"&TEXT(DAY($A8),"00"))=0,"",_xlfn.MINIFS(history!$H:$H,history!$C:$C,"tim",history!$D:$D,"postpaid",history!$A:$A,YEAR($A8)&"-"&TEXT(MONTH($A8),"00")&"-"&TEXT(DAY($A8),"00"))),"") -> 119.99 | F8: =IFERROR(IF(_xlfn.MINIFS(history!$H:$H,history!$C:$C,"vivo",history!$D:$D,"postpaid",history!$A:$A,YEAR($A8)&"-"&TEXT(MONTH($A8),"00")&"-"&TEXT(DAY($A8),"00"))=0,"",_xlfn.MINIFS(history!$H:$H,history!$C:$C,"vivo",history!$D:$D,"postpaid",history!$A:$A,YEAR($A8)&"-"&TEXT(MONTH($A8),"00")&"-"&TEXT(DAY($A8),"00"))),"") -> 150 | G8: =IFERROR(IF(_xlfn.MINIFS(history!$H:$H,history!$C:$C,"claro",history!$D:$D,"postpaid",history!$A:$A,YEAR($A8)&"-"&TEXT(MONTH($A8),"00")&"-"&TEXT(DAY($A8),"00"))=0,"",_xlfn.MINIFS(history!$H:$H,history!$C:$C,"claro",history!$D:$D,"postpaid",history!$A:$A,YEAR($A8)&"-"&TEXT(MONTH($A8),"00")&"-"&TEXT(DAY($A8),"00"))),"") -> 124.9 | H8: =IFERROR(IF(_xlfn.MINIFS(history!$H:$H,history!$C:$C,"tim",history!$D:$D,"prepaid",history!$A:$A,YEAR($A8)&"-"&TEXT(MONTH($A8),"00")&"-"&TEXT(DAY($A8),"00"),history!$N:$N,">=28")=0,"",_xlfn.MINIFS(history!$H:$H,history!$C:$C,"tim",history!$D:$D,"prepaid",history!$A:$A,YEAR($A8)&"-"&TEXT(MONTH($A8),"00")&"-"&TEXT(DAY($A8),"00"),history!$N:$N,">=28")),"") -> 20 | I8: =IFERROR(IF(_xlfn.MINIFS(history!$H:$H,history!$C:$C,"vivo",history!$D:$D,"prepaid",history!$A:$A,YEAR($A8)&"-"&TEXT(MONTH($A8),"00")&"-"&TEXT(DAY($A8),"00"),history!$N:$N,">=28")=0,"",_xlfn.MINIFS(history!$H:$H,history!$C:$C,"vivo",history!$D:$D,"prepaid",history!$A:$A,YEAR($A8)&"-"&TEXT(MONTH($A8),"00")&"-"&TEXT(DAY($A8),"00"),history!$N:$N,">=28")),"") -> 30 | J8: =IFERROR(IF(_xlfn.MINIFS(history!$H:$H,history!$C:$C,"claro",history!$D:$D,"prepaid",history!$A:$A,YEAR($A8)&"-"&TEXT(MONTH($A8),"00")&"-"&TEXT(DAY($A8),"00"),history!$N:$N,">=28")=0,"",_xlfn.MINIFS(history!$H:$H,history!$C:$C,"claro",history!$D:$D,"prepaid",history!$A:$A,YEAR($A8)&"-"&TEXT(MONTH($A8),"00")&"-"&TEXT(DAY($A8),"00"),history!$N:$N,">=28")),"") -> 30 | K8: =IFERROR(1/MAX(IFERROR(1/_xlfn.MINIFS(history!$H:$H,history!$C:$C,"tim",history!$D:$D,"lite",history!$A:$A,YEAR($A8)&"-"&TEXT(MONTH($A8),"00")&"-"&TEXT(DAY($A8),"00"),history!$S:$S,">0"),0),IFERROR(1/_xlfn.MINIFS(history!$H:$H,history!$C:$C,"tim",history!$D:$D,"flex",history!$A:$A,YEAR($A8)&"-"&TEXT(MONTH($A8),"00")&"-"&TEXT(DAY($A8),"00")),0),IFERROR(1/_xlfn.MINIFS(history!$H:$H,history!$C:$C,"tim",history!$D:$D,"fit",history!$A:$A,YEAR($A8)&"-"&TEXT(MONTH($A8),"00")&"-"&TEXT(DAY($A8),"00"),history!$S:$S,"="),0)),"") | L8: =IFERROR(1/MAX(IFERROR(1/_xlfn.MINIFS(history!$H:$H,history!$C:$C,"vivo",history!$D:$D,"lite",history!$A:$A,YEAR($A8)&"-"&TEXT(MONTH($A8),"00")&"-"&TEXT(DAY($A8),"00"),history!$S:$S,">0"),0),IFERROR(1/_xlfn.MINIFS(history!$H:$H,history!$C:$C,"vivo",history!$D:$D,"flex",history!$A:$A,YEAR($A8)&"-"&TEXT(MONTH($A8),"00")&"-"&TEXT(DAY($A8),"00")),0),IFERROR(1/_xlfn.MINIFS(history!$H:$H,history!$C:$C,"vivo",history!$D:$D,"fit",history!$A:$A,YEAR($A8)&"-"&TEXT(MONTH($A8),"00")&"-"&TEXT(DAY($A8),"00"),history!$S:$S,"="),0)),"") | M8: =IFERROR(1/MAX(IFERROR(1/_xlfn.MINIFS(history!$H:$H,history!$C:$C,"claro",history!$D:$D,"lite",history!$A:$A,YEAR($A8)&"-"&TEXT(MONTH($A8),"00")&"-"&TEXT(DAY($A8),"00"),history!$S:$S,">0"),0),IFERROR(1/_xlfn.MINIFS(history!$H:$H,history!$C:$C,"claro",history!$D:$D,"flex",history!$A:$A,YEAR($A8)&"-"&TEXT(MONTH($A8),"00")&"-"&TEXT(DAY($A8),"00")),0),IFERROR(1/_xlfn.MINIFS(history!$H:$H,history!$C:$C,"claro",history!$D:$D,"fit",history!$A:$A,YEAR($A8)&"-"&TEXT(MONTH($A8),"00")&"-"&TEXT(DAY($A8),"00"),history!$S:$S,"="),0)),"") -> 44.9
A9: 46201 | B9: =IFERROR(IF(_xlfn.MINIFS(history!$H:$H,history!$C:$C,"tim",history!$D:$D,"control",history!$A:$A,YEAR($A9)&"-"&TEXT(MONTH($A9),"00")&"-"&TEXT(DAY($A9),"00"))=0,"",_xlfn.MINIFS(history!$H:$H,history!$C:$C,"tim",history!$D:$D,"control",history!$A:$A,YEAR($A9)&"-"&TEXT(MONTH($A9),"00")&"-"&TEXT(DAY($A9),"00"))),"") -> 58.99 | C9: =IFERROR(IF(_xlfn.MINIFS(history!$H:$H,history!$C:$C,"vivo",history!$D:$D,"control",history!$A:$A,YEAR($A9)&"-"&TEXT(MONTH($A9),"00")&"-"&TEXT(DAY($A9),"00"))=0,"",_xlfn.MINIFS(history!$H:$H,history!$C:$C,"vivo",history!$D:$D,"control",history!$A:$A,YEAR($A9)&"-"&TEXT(MONTH($A9),"00")&"-"&TEXT(DAY($A9),"00"))),"") -> 59 | D9: =IFERROR(IF(_xlfn.MINIFS(history!$H:$H,history!$C:$C,"claro",history!$D:$D,"control",history!$A:$A,YEAR($A9)&"-"&TEXT(MONTH($A9),"00")&"-"&TEXT(DAY($A9),"00"))=0,"",_xlfn.MINIFS(history!$H:$H,history!$C:$C,"claro",history!$D:$D,"control",history!$A:$A,YEAR($A9)&"-"&TEXT(MONTH($A9),"00")&"-"&TEXT(DAY($A9),"00"))),"") -> 59.9 | E9: =IFERROR(IF(_xlfn.MINIFS(history!$H:$H,history!$C:$C,"tim",history!$D:$D,"postpaid",history!$A:$A,YEAR($A9)&"-"&TEXT(MONTH($A9),"00")&"-"&TEXT(DAY($A9),"00"))=0,"",_xlfn.MINIFS(history!$H:$H,history!$C:$C,"tim",history!$D:$D,"postpaid",history!$A:$A,YEAR($A9)&"-"&TEXT(MONTH($A9),"00")&"-"&TEXT(DAY($A9),"00"))),"") -> 119.99 | F9: =IFERROR(IF(_xlfn.MINIFS(history!$H:$H,history!$C:$C,"vivo",history!$D:$D,"postpaid",history!$A:$A,YEAR($A9)&"-"&TEXT(MONTH($A9),"00")&"-"&TEXT(DAY($A9),"00"))=0,"",_xlfn.MINIFS(history!$H:$H,history!$C:$C,"vivo",history!$D:$D,"postpaid",history!$A:$A,YEAR($A9)&"-"&TEXT(MONTH($A9),"00")&"-"&TEXT(DAY($A9),"00"))),"") -> 150 | G9: =IFERROR(IF(_xlfn.MINIFS(history!$H:$H,history!$C:$C,"claro",history!$D:$D,"postpaid",history!$A:$A,YEAR($A9)&"-"&TEXT(MONTH($A9),"00")&"-"&TEXT(DAY($A9),"00"))=0,"",_xlfn.MINIFS(history!$H:$H,history!$C:$C,"claro",history!$D:$D,"postpaid",history!$A:$A,YEAR($A9)&"-"&TEXT(MONTH($A9),"00")&"-"&TEXT(DAY($A9),"00"))),"") -> 124.9 | H9: =IFERROR(IF(_xlfn.MINIFS(history!$H:$H,history!$C:$C,"tim",history!$D:$D,"prepaid",history!$A:$A,YEAR($A9)&"-"&TEXT(MONTH($A9),"00")&"-"&TEXT(DAY($A9),"00"),history!$N:$N,">=28")=0,"",_xlfn.MINIFS(history!$H:$H,history!$C:$C,"tim",history!$D:$D,"prepaid",history!$A:$A,YEAR($A9)&"-"&TEXT(MONTH($A9),"00")&"-"&TEXT(DAY($A9),"00"),history!$N:$N,">=28")),"") -> 20 | I9: =IFERROR(IF(_xlfn.MINIFS(history!$H:$H,history!$C:$C,"vivo",history!$D:$D,"prepaid",history!$A:$A,YEAR($A9)&"-"&TEXT(MONTH($A9),"00")&"-"&TEXT(DAY($A9),"00"),history!$N:$N,">=28")=0,"",_xlfn.MINIFS(history!$H:$H,history!$C:$C,"vivo",history!$D:$D,"prepaid",history!$A:$A,YEAR($A9)&"-"&TEXT(MONTH($A9),"00")&"-"&TEXT(DAY($A9),"00"),history!$N:$N,">=28")),"") -> 30 | J9: =IFERROR(IF(_xlfn.MINIFS(history!$H:$H,history!$C:$C,"claro",history!$D:$D,"prepaid",history!$A:$A,YEAR($A9)&"-"&TEXT(MONTH($A9),"00")&"-"&TEXT(DAY($A9),"00"),history!$N:$N,">=28")=0,"",_xlfn.MINIFS(history!$H:$H,history!$C:$C,"claro",history!$D:$D,"prepaid",history!$A:$A,YEAR($A9)&"-"&TEXT(MONTH($A9),"00")&"-"&TEXT(DAY($A9),"00"),history!$N:$N,">=28")),"") -> 30 | K9: =IFERROR(1/MAX(IFERROR(1/_xlfn.MINIFS(history!$H:$H,history!$C:$C,"tim",history!$D:$D,"lite",history!$A:$A,YEAR($A9)&"-"&TEXT(MONTH($A9),"00")&"-"&TEXT(DAY($A9),"00"),history!$S:$S,">0"),0),IFERROR(1/_xlfn.MINIFS(history!$H:$H,history!$C:$C,"tim",history!$D:$D,"flex",history!$A:$A,YEAR($A9)&"-"&TEXT(MONTH($A9),"00")&"-"&TEXT(DAY($A9),"00")),0),IFERROR(1/_xlfn.MINIFS(history!$H:$H,history!$C:$C,"tim",history!$D:$D,"fit",history!$A:$A,YEAR($A9)&"-"&TEXT(MONTH($A9),"00")&"-"&TEXT(DAY($A9),"00"),history!$S:$S,"="),0)),"") | L9: =IFERROR(1/MAX(IFERROR(1/_xlfn.MINIFS(history!$H:$H,history!$C:$C,"vivo",history!$D:$D,"lite",history!$A:$A,YEAR($A9)&"-"&TEXT(MONTH($A9),"00")&"-"&TEXT(DAY($A9),"00"),history!$S:$S,">0"),0),IFERROR(1/_xlfn.MINIFS(history!$H:$H,history!$C:$C,"vivo",history!$D:$D,"flex",history!$A:$A,YEAR($A9)&"-"&TEXT(MONTH($A9),"00")&"-"&TEXT(DAY($A9),"00")),0),IFERROR(1/_xlfn.MINIFS(history!$H:$H,history!$C:$C,"vivo",history!$D:$D,"fit",history!$A:$A,YEAR($A9)&"-"&TEXT(MONTH($A9),"00")&"-"&TEXT(DAY($A9),"00"),history!$S:$S,"="),0)),"") | M9: =IFERROR(1/MAX(IFERROR(1/_xlfn.MINIFS(history!$H:$H,history!$C:$C,"claro",history!$D:$D,"lite",history!$A:$A,YEAR($A9)&"-"&TEXT(MONTH($A9),"00")&"-"&TEXT(DAY($A9),"00"),history!$S:$S,">0"),0),IFERROR(1/_xlfn.MINIFS(history!$H:$H,history!$C:$C,"claro",history!$D:$D,"flex",history!$A:$A,YEAR($A9)&"-"&TEXT(MONTH($A9),"00")&"-"&TEXT(DAY($A9),"00")),0),IFERROR(1/_xlfn.MINIFS(history!$H:$H,history!$C:$C,"claro",history!$D:$D,"fit",history!$A:$A,YEAR($A9)&"-"&TEXT(MONTH($A9),"00")&"-"&TEXT(DAY($A9),"00"),history!$S:$S,"="),0)),"") -> 44.9
A10: 46202 | B10: =IFERROR(IF(_xlfn.MINIFS(history!$H:$H,history!$C:$C,"tim",history!$D:$D,"control",history!$A:$A,YEAR($A10)&"-"&TEXT(MONTH($A10),"00")&"-"&TEXT(DAY($A10),"00"))=0,"",_xlfn.MINIFS(history!$H:$H,history!$C:$C,"tim",history!$D:$D,"control",history!$A:$A,YEAR($A10)&"-"&TEXT(MONTH($A10),"00")&"-"&TEXT(DAY($A10),"00"))),"") -> 58.99 | C10: =IFERROR(IF(_xlfn.MINIFS(history!$H:$H,history!$C:$C,"vivo",history!$D:$D,"control",history!$A:$A,YEAR($A10)&"-"&TEXT(MONTH($A10),"00")&"-"&TEXT(DAY($A10),"00"))=0,"",_xlfn.MINIFS(history!$H:$H,history!$C:$C,"vivo",history!$D:$D,"control",history!$A:$A,YEAR($A10)&"-"&TEXT(MONTH($A10),"00")&"-"&TEXT(DAY($A10),"00"))),"") -> 59 | D10: =IFERROR(IF(_xlfn.MINIFS(history!$H:$H,history!$C:$C,"claro",history!$D:$D,"control",history!$A:$A,YEAR($A10)&"-"&TEXT(MONTH($A10),"00")&"-"&TEXT(DAY($A10),"00"))=0,"",_xlfn.MINIFS(history!$H:$H,history!$C:$C,"claro",history!$D:$D,"control",history!$A:$A,YEAR($A10)&"-"&TEXT(MONTH($A10),"00")&"-"&TEXT(DAY($A10),"00"))),"") -> 59.9 | E10: =IFERROR(IF(_xlfn.MINIFS(history!$H:$H,history!$C:$C,"tim",history!$D:$D,"postpaid",history!$A:$A,YEAR($A10)&"-"&TEXT(MONTH($A10),"00")&"-"&TEXT(DAY($A10),"00"))=0,"",_xlfn.MINIFS(history!$H:$H,history!$C:$C,"tim",history!$D:$D,"postpaid",history!$A:$A,YEAR($A10)&"-"&TEXT(MONTH($A10),"00")&"-"&TEXT(DAY($A10),"00"))),"") -> 119.99 | F10: =IFERROR(IF(_xlfn.MINIFS(history!$H:$H,history!$C:$C,"vivo",history!$D:$D,"postpaid",history!$A:$A,YEAR($A10)&"-"&TEXT(MONTH($A10),"00")&"-"&TEXT(DAY($A10),"00"))=0,"",_xlfn.MINIFS(history!$H:$H,history!$C:$C,"vivo",history!$D:$D,"postpaid",history!$A:$A,YEAR($A10)&"-"&TEXT(MONTH($A10),"00")&"-"&TEXT(DAY($A10),"00"))),"") -> 150 | G10: =IFERROR(IF(_xlfn.MINIFS(history!$H:$H,history!$C:$C,"claro",history!$D:$D,"postpaid",history!$A:$A,YEAR($A10)&"-"&TEXT(MONTH($A10),"00")&"-"&TEXT(DAY($A10),"00"))=0,"",_xlfn.MINIFS(history!$H:$H,history!$C:$C,"claro",history!$D:$D,"postpaid",history!$A:$A,YEAR($A10)&"-"&TEXT(MONTH($A10),"00")&"-"&TEXT(DAY($A10),"00"))),"") -> 124.9 | H10: =IFERROR(IF(_xlfn.MINIFS(history!$H:$H,history!$C:$C,"tim",history!$D:$D,"prepaid",history!$A:$A,YEAR($A10)&"-"&TEXT(MONTH($A10),"00")&"-"&TEXT(DAY($A10),"00"),history!$N:$N,">=28")=0,"",_xlfn.MINIFS(history!$H:$H,history!$C:$C,"tim",history!$D:$D,"prepaid",history!$A:$A,YEAR($A10)&"-"&TEXT(MONTH($A10),"00")&"-"&TEXT(DAY($A10),"00"),history!$N:$N,">=28")),"") -> 20 | I10: =IFERROR(IF(_xlfn.MINIFS(history!$H:$H,history!$C:$C,"vivo",history!$D:$D,"prepaid",history!$A:$A,YEAR($A10)&"-"&TEXT(MONTH($A10),"00")&"-"&TEXT(DAY($A10),"00"),history!$N:$N,">=28")=0,"",_xlfn.MINIFS(history!$H:$H,history!$C:$C,"vivo",history!$D:$D,"prepaid",history!$A:$A,YEAR($A10)&"-"&TEXT(MONTH($A10),"00")&"-"&TEXT(DAY($A10),"00"),history!$N:$N,">=28")),"") -> 30 | J10: =IFERROR(IF(_xlfn.MINIFS(history!$H:$H,history!$C:$C,"claro",history!$D:$D,"prepaid",history!$A:$A,YEAR($A10)&"-"&TEXT(MONTH($A10),"00")&"-"&TEXT(DAY($A10),"00"),history!$N:$N,">=28")=0,"",_xlfn.MINIFS(history!$H:$H,history!$C:$C,"claro",history!$D:$D,"prepaid",history!$A:$A,YEAR($A10)&"-"&TEXT(MONTH($A10),"00")&"-"&TEXT(DAY($A10),"00"),history!$N:$N,">=28")),"") -> 30 | K10: =IFERROR(1/MAX(IFERROR(1/_xlfn.MINIFS(history!$H:$H,history!$C:$C,"tim",history!$D:$D,"lite",history!$A:$A,YEAR($A10)&"-"&TEXT(MONTH($A10),"00")&"-"&TEXT(DAY($A10),"00"),history!$S:$S,">0"),0),IFERROR(1/_xlfn.MINIFS(history!$H:$H,history!$C:$C,"tim",history!$D:$D,"flex",history!$A:$A,YEAR($A10)&"-"&TEXT(MONTH($A10),"00")&"-"&TEXT(DAY($A10),"00")),0),IFERROR(1/_xlfn.MINIFS(history!$H:$H,history!$C:$C,"tim",history!$D:$D,"fit",history!$A:$A,YEAR($A10)&"-"&TEXT(MONTH($A10),"00")&"-"&TEXT(DAY($A10),"00"),history!$S:$S,"="),0)),"") | L10: =IFERROR(1/MAX(IFERROR(1/_xlfn.MINIFS(history!$H:$H,history!$C:$C,"vivo",history!$D:$D,"lite",history!$A:$A,YEAR($A10)&"-"&TEXT(MONTH($A10),"00")&"-"&TEXT(DAY($A10),"00"),history!$S:$S,">0"),0),IFERROR(1/_xlfn.MINIFS(history!$H:$H,history!$C:$C,"vivo",history!$D:$D,"flex",history!$A:$A,YEAR($A10)&"-"&TEXT(MONTH($A10),"00")&"-"&TEXT(DAY($A10),"00")),0),IFERROR(1/_xlfn.MINIFS(history!$H:$H,history!$C:$C,"vivo",history!$D:$D,"fit",history!$A:$A,YEAR($A10)&"-"&TEXT(MONTH($A10),"00")&"-"&TEXT(DAY($A10),"00"),history!$S:$S,"="),0)),"") | M10: =IFERROR(1/MAX(IFERROR(1/_xlfn.MINIFS(history!$H:$H,history!$C:$C,"claro",history!$D:$D,"lite",history!$A:$A,YEAR($A10)&"-"&TEXT(MONTH($A10),"00")&"-"&TEXT(DAY($A10),"00"),history!$S:$S,">0"),0),IFERROR(1/_xlfn.MINIFS(history!$H:$H,history!$C:$C,"claro",history!$D:$D,"flex",history!$A:$A,YEAR($A10)&"-"&TEXT(MONTH($A10),"00")&"-"&TEXT(DAY($A10),"00")),0),IFERROR(1/_xlfn.MINIFS(history!$H:$H,history!$C:$C,"claro",history!$D:$D,"fit",history!$A:$A,YEAR($A10)&"-"&TEXT(MONTH($A10),"00")&"-"&TEXT(DAY($A10),"00"),history!$S:$S,"="),0)),"") -> 44.9
A11: 46203 | B11: =IFERROR(IF(_xlfn.MINIFS(history!$H:$H,history!$C:$C,"tim",history!$D:$D,"control",history!$A:$A,YEAR($A11)&"-"&TEXT(MONTH($A11),"00")&"-"&TEXT(DAY($A11),"00"))=0,"",_xlfn.MINIFS(history!$H:$H,history!$C:$C,"tim",history!$D:$D,"control",history!$A:$A,YEAR($A11)&"-"&TEXT(MONTH($A11),"00")&"-"&TEXT(DAY($A11),"00"))),"") -> 58.99 | C11: =IFERROR(IF(_xlfn.MINIFS(history!$H:$H,history!$C:$C,"vivo",history!$D:$D,"control",history!$A:$A,YEAR($A11)&"-"&TEXT(MONTH($A11),"00")&"-"&TEXT(DAY($A11),"00"))=0,"",_xlfn.MINIFS(history!$H:$H,history!$C:$C,"vivo",history!$D:$D,"control",history!$A:$A,YEAR($A11)&"-"&TEXT(MONTH($A11),"00")&"-"&TEXT(DAY($A11),"00"))),"") -> 59 | D11: =IFERROR(IF(_xlfn.MINIFS(history!$H:$H,history!$C:$C,"claro",history!$D:$D,"control",history!$A:$A,YEAR($A11)&"-"&TEXT(MONTH($A11),"00")&"-"&TEXT(DAY($A11),"00"))=0,"",_xlfn.MINIFS(history!$H:$H,history!$C:$C,"claro",history!$D:$D,"control",history!$A:$A,YEAR($A11)&"-"&TEXT(MONTH($A11),"00")&"-"&TEXT(DAY($A11),"00"))),"") -> 59.9 | E11: =IFERROR(IF(_xlfn.MINIFS(history!$H:$H,history!$C:$C,"tim",history!$D:$D,"postpaid",history!$A:$A,YEAR($A11)&"-"&TEXT(MONTH($A11),"00")&"-"&TEXT(DAY($A11),"00"))=0,"",_xlfn.MINIFS(history!$H:$H,history!$C:$C,"tim",history!$D:$D,"postpaid",history!$A:$A,YEAR($A11)&"-"&TEXT(MONTH($A11),"00")&"-"&TEXT(DAY($A11),"00"))),"") -> 119.99 | F11: =IFERROR(IF(_xlfn.MINIFS(history!$H:$H,history!$C:$C,"vivo",history!$D:$D,"postpaid",history!$A:$A,YEAR($A11)&"-"&TEXT(MONTH($A11),"00")&"-"&TEXT(DAY($A11),"00"))=0,"",_xlfn.MINIFS(history!$H:$H,history!$C:$C,"vivo",history!$D:$D,"postpaid",history!$A:$A,YEAR($A11)&"-"&TEXT(MONTH($A11),"00")&"-"&TEXT(DAY($A11),"00"))),"") -> 150 | G11: =IFERROR(IF(_xlfn.MINIFS(history!$H:$H,history!$C:$C,"claro",history!$D:$D,"postpaid",history!$A:$A,YEAR($A11)&"-"&TEXT(MONTH($A11),"00")&"-"&TEXT(DAY($A11),"00"))=0,"",_xlfn.MINIFS(history!$H:$H,history!$C:$C,"claro",history!$D:$D,"postpaid",history!$A:$A,YEAR($A11)&"-"&TEXT(MONTH($A11),"00")&"-"&TEXT(DAY($A11),"00"))),"") -> 124.9 | H11: =IFERROR(IF(_xlfn.MINIFS(history!$H:$H,history!$C:$C,"tim",history!$D:$D,"prepaid",history!$A:$A,YEAR($A11)&"-"&TEXT(MONTH($A11),"00")&"-"&TEXT(DAY($A11),"00"),history!$N:$N,">=28")=0,"",_xlfn.MINIFS(history!$H:$H,history!$C:$C,"tim",history!$D:$D,"prepaid",history!$A:$A,YEAR($A11)&"-"&TEXT(MONTH($A11),"00")&"-"&TEXT(DAY($A11),"00"),history!$N:$N,">=28")),"") -> 20 | I11: =IFERROR(IF(_xlfn.MINIFS(history!$H:$H,history!$C:$C,"vivo",history!$D:$D,"prepaid",history!$A:$A,YEAR($A11)&"-"&TEXT(MONTH($A11),"00")&"-"&TEXT(DAY($A11),"00"),history!$N:$N,">=28")=0,"",_xlfn.MINIFS(history!$H:$H,history!$C:$C,"vivo",history!$D:$D,"prepaid",history!$A:$A,YEAR($A11)&"-"&TEXT(MONTH($A11),"00")&"-"&TEXT(DAY($A11),"00"),history!$N:$N,">=28")),"") -> 30 | J11: =IFERROR(IF(_xlfn.MINIFS(history!$H:$H,history!$C:$C,"claro",history!$D:$D,"prepaid",history!$A:$A,YEAR($A11)&"-"&TEXT(MONTH($A11),"00")&"-"&TEXT(DAY($A11),"00"),history!$N:$N,">=28")=0,"",_xlfn.MINIFS(history!$H:$H,history!$C:$C,"claro",history!$D:$D,"prepaid",history!$A:$A,YEAR($A11)&"-"&TEXT(MONTH($A11),"00")&"-"&TEXT(DAY($A11),"00"),history!$N:$N,">=28")),"") -> 30 | K11: =IFERROR(1/MAX(IFERROR(1/_xlfn.MINIFS(history!$H:$H,history!$C:$C,"tim",history!$D:$D,"lite",history!$A:$A,YEAR($A11)&"-"&TEXT(MONTH($A11),"00")&"-"&TEXT(DAY($A11),"00"),history!$S:$S,">0"),0),IFERROR(1/_xlfn.MINIFS(history!$H:$H,history!$C:$C,"tim",history!$D:$D,"flex",history!$A:$A,YEAR($A11)&"-"&TEXT(MONTH($A11),"00")&"-"&TEXT(DAY($A11),"00")),0),IFERROR(1/_xlfn.MINIFS(history!$H:$H,history!$C:$C,"tim",history!$D:$D,"fit",history!$A:$A,YEAR($A11)&"-"&TEXT(MONTH($A11),"00")&"-"&TEXT(DAY($A11),"00"),history!$S:$S,"="),0)),"") | L11: =IFERROR(1/MAX(IFERROR(1/_xlfn.MINIFS(history!$H:$H,history!$C:$C,"vivo",history!$D:$D,"lite",history!$A:$A,YEAR($A11)&"-"&TEXT(MONTH($A11),"00")&"-"&TEXT(DAY($A11),"00"),history!$S:$S,">0"),0),IFERROR(1/_xlfn.MINIFS(history!$H:$H,history!$C:$C,"vivo",history!$D:$D,"flex",history!$A:$A,YEAR($A11)&"-"&TEXT(MONTH($A11),"00")&"-"&TEXT(DAY($A11),"00")),0),IFERROR(1/_xlfn.MINIFS(history!$H:$H,history!$C:$C,"vivo",history!$D:$D,"fit",history!$A:$A,YEAR($A11)&"-"&TEXT(MONTH($A11),"00")&"-"&TEXT(DAY($A11),"00"),history!$S:$S,"="),0)),"") | M11: =IFERROR(1/MAX(IFERROR(1/_xlfn.MINIFS(history!$H:$H,history!$C:$C,"claro",history!$D:$D,"lite",history!$A:$A,YEAR($A11)&"-"&TEXT(MONTH($A11),"00")&"-"&TEXT(DAY($A11),"00"),history!$S:$S,">0"),0),IFERROR(1/_xlfn.MINIFS(history!$H:$H,history!$C:$C,"claro",history!$D:$D,"flex",history!$A:$A,YEAR($A11)&"-"&TEXT(MONTH($A11),"00")&"-"&TEXT(DAY($A11),"00")),0),IFERROR(1/_xlfn.MINIFS(history!$H:$H,history!$C:$C,"claro",history!$D:$D,"fit",history!$A:$A,YEAR($A11)&"-"&TEXT(MONTH($A11),"00")&"-"&TEXT(DAY($A11),"00"),history!$S:$S,"="),0)),"") -> 44.9
A12: 46204 | B12: =IFERROR(IF(_xlfn.MINIFS(history!$H:$H,history!$C:$C,"tim",history!$D:$D,"control",history!$A:$A,YEAR($A12)&"-"&TEXT(MONTH($A12),"00")&"-"&TEXT(DAY($A12),"00"))=0,"",_xlfn.MINIFS(history!$H:$H,history!$C:$C,"tim",history!$D:$D,"control",history!$A:$A,YEAR($A12)&"-"&TEXT(MONTH($A12),"00")&"-"&TEXT(DAY($A12),"00"))),"") -> 58.99 | C12: =IFERROR(IF(_xlfn.MINIFS(history!$H:$H,history!$C:$C,"vivo",history!$D:$D,"control",history!$A:$A,YEAR($A12)&"-"&TEXT(MONTH($A12),"00")&"-"&TEXT(DAY($A12),"00"))=0,"",_xlfn.MINIFS(history!$H:$H,history!$C:$C,"vivo",history!$D:$D,"control",history!$A:$A,YEAR($A12)&"-"&TEXT(MONTH($A12),"00")&"-"&TEXT(DAY($A12),"00"))),"") -> 59 | D12: =IFERROR(IF(_xlfn.MINIFS(history!$H:$H,history!$C:$C,"claro",history!$D:$D,"control",history!$A:$A,YEAR($A12)&"-"&TEXT(MONTH($A12),"00")&"-"&TEXT(DAY($A12),"00"))=0,"",_xlfn.MINIFS(history!$H:$H,history!$C:$C,"claro",history!$D:$D,"control",history!$A:$A,YEAR($A12)&"-"&TEXT(MONTH($A12),"00")&"-"&TEXT(DAY($A12),"00"))),"") -> 59.9 | E12: =IFERROR(IF(_xlfn.MINIFS(history!$H:$H,history!$C:$C,"tim",history!$D:$D,"postpaid",history!$A:$A,YEAR($A12)&"-"&TEXT(MONTH($A12),"00")&"-"&TEXT(DAY($A12),"00"))=0,"",_xlfn.MINIFS(history!$H:$H,history!$C:$C,"tim",history!$D:$D,"postpaid",history!$A:$A,YEAR($A12)&"-"&TEXT(MONTH($A12),"00")&"-"&TEXT(DAY($A12),"00"))),"") -> 119.99 | F12: =IFERROR(IF(_xlfn.MINIFS(history!$H:$H,history!$C:$C,"vivo",history!$D:$D,"postpaid",history!$A:$A,YEAR($A12)&"-"&TEXT(MONTH($A12),"00")&"-"&TEXT(DAY($A12),"00"))=0,"",_xlfn.MINIFS(history!$H:$H,history!$C:$C,"vivo",history!$D:$D,"postpaid",history!$A:$A,YEAR($A12)&"-"&TEXT(MONTH($A12),"00")&"-"&TEXT(DAY($A12),"00"))),"") -> 150 | G12: =IFERROR(IF(_xlfn.MINIFS(history!$H:$H,history!$C:$C,"claro",history!$D:$D,"postpaid",history!$A:$A,YEAR($A12)&"-"&TEXT(MONTH($A12),"00")&"-"&TEXT(DAY($A12),"00"))=0,"",_xlfn.MINIFS(history!$H:$H,history!$C:$C,"claro",history!$D:$D,"postpaid",history!$A:$A,YEAR($A12)&"-"&TEXT(MONTH($A12),"00")&"-"&TEXT(DAY($A12),"00"))),"") -> 124.9 | H12: =IFERROR(IF(_xlfn.MINIFS(history!$H:$H,history!$C:$C,"tim",history!$D:$D,"prepaid",history!$A:$A,YEAR($A12)&"-"&TEXT(MONTH($A12),"00")&"-"&TEXT(DAY($A12),"00"),history!$N:$N,">=28")=0,"",_xlfn.MINIFS(history!$H:$H,history!$C:$C,"tim",history!$D:$D,"prepaid",history!$A:$A,YEAR($A12)&"-"&TEXT(MONTH($A12),"00")&"-"&TEXT(DAY($A12),"00"),history!$N:$N,">=28")),"") -> 30 | I12: =IFERROR(IF(_xlfn.MINIFS(history!$H:$H,history!$C:$C,"vivo",history!$D:$D,"prepaid",history!$A:$A,YEAR($A12)&"-"&TEXT(MONTH($A12),"00")&"-"&TEXT(DAY($A12),"00"),history!$N:$N,">=28")=0,"",_xlfn.MINIFS(history!$H:$H,history!$C:$C,"vivo",history!$D:$D,"prepaid",history!$A:$A,YEAR($A12)&"-"&TEXT(MONTH($A12),"00")&"-"&TEXT(DAY($A12),"00"),history!$N:$N,">=28")),"") -> 30 | J12: =IFERROR(IF(_xlfn.MINIFS(history!$H:$H,history!$C:$C,"claro",history!$D:$D,"prepaid",history!$A:$A,YEAR($A12)&"-"&TEXT(MONTH($A12),"00")&"-"&TEXT(DAY($A12),"00"),history!$N:$N,">=28")=0,"",_xlfn.MINIFS(history!$H:$H,history!$C:$C,"claro",history!$D:$D,"prepaid",history!$A:$A,YEAR($A12)&"-"&TEXT(MONTH($A12),"00")&"-"&TEXT(DAY($A12),"00"),history!$N:$N,">=28")),"") -> 30 | K12: =IFERROR(1/MAX(IFERROR(1/_xlfn.MINIFS(history!$H:$H,history!$C:$C,"tim",history!$D:$D,"lite",history!$A:$A,YEAR($A12)&"-"&TEXT(MONTH($A12),"00")&"-"&TEXT(DAY($A12),"00"),history!$S:$S,">0"),0),IFERROR(1/_xlfn.MINIFS(history!$H:$H,history!$C:$C,"tim",history!$D:$D,"flex",history!$A:$A,YEAR($A12)&"-"&TEXT(MONTH($A12),"00")&"-"&TEXT(DAY($A12),"00")),0),IFERROR(1/_xlfn.MINIFS(history!$H:$H,history!$C:$C,"tim",history!$D:$D,"fit",history!$A:$A,YEAR($A12)&"-"&TEXT(MONTH($A12),"00")&"-"&TEXT(DAY($A12),"00"),history!$S:$S,"="),0)),"") | L12: =IFERROR(1/MAX(IFERROR(1/_xlfn.MINIFS(history!$H:$H,history!$C:$C,"vivo",history!$D:$D,"lite",history!$A:$A,YEAR($A12)&"-"&TEXT(MONTH($A12),"00")&"-"&TEXT(DAY($A12),"00"),history!$S:$S,">0"),0),IFERROR(1/_xlfn.MINIFS(history!$H:$H,history!$C:$C,"vivo",history!$D:$D,"flex",history!$A:$A,YEAR($A12)&"-"&TEXT(MONTH($A12),"00")&"-"&TEXT(DAY($A12),"00")),0),IFERROR(1/_xlfn.MINIFS(history!$H:$H,history!$C:$C,"vivo",history!$D:$D,"fit",history!$A:$A,YEAR($A12)&"-"&TEXT(MONTH($A12),"00")&"-"&TEXT(DAY($A12),"00"),history!$S:$S,"="),0)),"") -> 45 | M12: =IFERROR(1/MAX(IFERROR(1/_xlfn.MINIFS(history!$H:$H,history!$C:$C,"claro",history!$D:$D,"lite",history!$A:$A,YEAR($A12)&"-"&TEXT(MONTH($A12),"00")&"-"&TEXT(DAY($A12),"00"),history!$S:$S,">0"),0),IFERROR(1/_xlfn.MINIFS(history!$H:$H,history!$C:$C,"claro",history!$D:$D,"flex",history!$A:$A,YEAR($A12)&"-"&TEXT(MONTH($A12),"00")&"-"&TEXT(DAY($A12),"00")),0),IFERROR(1/_xlfn.MINIFS(history!$H:$H,history!$C:$C,"claro",history!$D:$D,"fit",history!$A:$A,YEAR($A12)&"-"&TEXT(MONTH($A12),"00")&"-"&TEXT(DAY($A12),"00"),history!$S:$S,"="),0)),"") -> 44.9
A13: 46205 | B13: =IFERROR(IF(_xlfn.MINIFS(history!$H:$H,history!$C:$C,"tim",history!$D:$D,"control",history!$A:$A,YEAR($A13)&"-"&TEXT(MONTH($A13),"00")&"-"&TEXT(DAY($A13),"00"))=0,"",_xlfn.MINIFS(history!$H:$H,history!$C:$C,"tim",history!$D:$D,"control",history!$A:$A,YEAR($A13)&"-"&TEXT(MONTH($A13),"00")&"-"&TEXT(DAY($A13),"00"))),"") -> 58.99 | C13: =IFERROR(IF(_xlfn.MINIFS(history!$H:$H,history!$C:$C,"vivo",history!$D:$D,"control",history!$A:$A,YEAR($A13)&"-"&TEXT(MONTH($A13),"00")&"-"&TEXT(DAY($A13),"00"))=0,"",_xlfn.MINIFS(history!$H:$H,history!$C:$C,"vivo",history!$D:$D,"control",history!$A:$A,YEAR($A13)&"-"&TEXT(MONTH($A13),"00")&"-"&TEXT(DAY($A13),"00"))),"") -> 59 | D13: =IFERROR(IF(_xlfn.MINIFS(history!$H:$H,history!$C:$C,"claro",history!$D:$D,"control",history!$A:$A,YEAR($A13)&"-"&TEXT(MONTH($A13),"00")&"-"&TEXT(DAY($A13),"00"))=0,"",_xlfn.MINIFS(history!$H:$H,history!$C:$C,"claro",history!$D:$D,"control",history!$A:$A,YEAR($A13)&"-"&TEXT(MONTH($A13),"00")&"-"&TEXT(DAY($A13),"00"))),"") -> 59.9 | E13: =IFERROR(IF(_xlfn.MINIFS(history!$H:$H,history!$C:$C,"tim",history!$D:$D,"postpaid",history!$A:$A,YEAR($A13)&"-"&TEXT(MONTH($A13),"00")&"-"&TEXT(DAY($A13),"00"))=0,"",_xlfn.MINIFS(history!$H:$H,history!$C:$C,"tim",history!$D:$D,"postpaid",history!$A:$A,YEAR($A13)&"-"&TEXT(MONTH($A13),"00")&"-"&TEXT(DAY($A13),"00"))),"") -> 119.99 | F13: =IFERROR(IF(_xlfn.MINIFS(history!$H:$H,history!$C:$C,"vivo",history!$D:$D,"postpaid",history!$A:$A,YEAR($A13)&"-"&TEXT(MONTH($A13),"00")&"-"&TEXT(DAY($A13),"00"))=0,"",_xlfn.MINIFS(history!$H:$H,history!$C:$C,"vivo",history!$D:$D,"postpaid",history!$A:$A,YEAR($A13)&"-"&TEXT(MONTH($A13),"00")&"-"&TEXT(DAY($A13),"00"))),"") -> 150 | G13: =IFERROR(IF(_xlfn.MINIFS(history!$H:$H,history!$C:$C,"claro",history!$D:$D,"postpaid",history!$A:$A,YEAR($A13)&"-"&TEXT(MONTH($A13),"00")&"-"&TEXT(DAY($A13),"00"))=0,"",_xlfn.MINIFS(history!$H:$H,history!$C:$C,"claro",history!$D:$D,"postpaid",history!$A:$A,YEAR($A13)&"-"&TEXT(MONTH($A13),"00")&"-"&TEXT(DAY($A13),"00"))),"") -> 124.9 | H13: =IFERROR(IF(_xlfn.MINIFS(history!$H:$H,history!$C:$C,"tim",history!$D:$D,"prepaid",history!$A:$A,YEAR($A13)&"-"&TEXT(MONTH($A13),"00")&"-"&TEXT(DAY($A13),"00"),history!$N:$N,">=28")=0,"",_xlfn.MINIFS(history!$H:$H,history!$C:$C,"tim",history!$D:$D,"prepaid",history!$A:$A,YEAR($A13)&"-"&TEXT(MONTH($A13),"00")&"-"&TEXT(DAY($A13),"00"),history!$N:$N,">=28")),"") -> 30 | I13: =IFERROR(IF(_xlfn.MINIFS(history!$H:$H,history!$C:$C,"vivo",history!$D:$D,"prepaid",history!$A:$A,YEAR($A13)&"-"&TEXT(MONTH($A13),"00")&"-"&TEXT(DAY($A13),"00"),history!$N:$N,">=28")=0,"",_xlfn.MINIFS(history!$H:$H,history!$C:$C,"vivo",history!$D:$D,"prepaid",history!$A:$A,YEAR($A13)&"-"&TEXT(MONTH($A13),"00")&"-"&TEXT(DAY($A13),"00"),history!$N:$N,">=28")),"") -> 30 | J13: =IFERROR(IF(_xlfn.MINIFS(history!$H:$H,history!$C:$C,"claro",history!$D:$D,"prepaid",history!$A:$A,YEAR($A13)&"-"&TEXT(MONTH($A13),"00")&"-"&TEXT(DAY($A13),"00"),history!$N:$N,">=28")=0,"",_xlfn.MINIFS(history!$H:$H,history!$C:$C,"claro",history!$D:$D,"prepaid",history!$A:$A,YEAR($A13)&"-"&TEXT(MONTH($A13),"00")&"-"&TEXT(DAY($A13),"00"),history!$N:$N,">=28")),"") -> 30 | K13: =IFERROR(1/MAX(IFERROR(1/_xlfn.MINIFS(history!$H:$H,history!$C:$C,"tim",history!$D:$D,"lite",history!$A:$A,YEAR($A13)&"-"&TEXT(MONTH($A13),"00")&"-"&TEXT(DAY($A13),"00"),history!$S:$S,">0"),0),IFERROR(1/_xlfn.MINIFS(history!$H:$H,history!$C:$C,"tim",history!$D:$D,"flex",history!$A:$A,YEAR($A13)&"-"&TEXT(MONTH($A13),"00")&"-"&TEXT(DAY($A13),"00")),0),IFERROR(1/_xlfn.MINIFS(history!$H:$H,history!$C:$C,"tim",history!$D:$D,"fit",history!$A:$A,YEAR($A13)&"-"&TEXT(MONTH($A13),"00")&"-"&TEXT(DAY($A13),"00"),history!$S:$S,"="),0)),"") | L13: =IFERROR(1/MAX(IFERROR(1/_xlfn.MINIFS(history!$H:$H,history!$C:$C,"vivo",history!$D:$D,"lite",history!$A:$A,YEAR($A13)&"-"&TEXT(MONTH($A13),"00")&"-"&TEXT(DAY($A13),"00"),history!$S:$S,">0"),0),IFERROR(1/_xlfn.MINIFS(history!$H:$H,history!$C:$C,"vivo",history!$D:$D,"flex",history!$A:$A,YEAR($A13)&"-"&TEXT(MONTH($A13),"00")&"-"&TEXT(DAY($A13),"00")),0),IFERROR(1/_xlfn.MINIFS(history!$H:$H,history!$C:$C,"vivo",history!$D:$D,"fit",history!$A:$A,YEAR($A13)&"-"&TEXT(MONTH($A13),"00")&"-"&TEXT(DAY($A13),"00"),history!$S:$S,"="),0)),"") -> 45 | M13: =IFERROR(1/MAX(IFERROR(1/_xlfn.MINIFS(history!$H:$H,history!$C:$C,"claro",history!$D:$D,"lite",history!$A:$A,YEAR($A13)&"-"&TEXT(MONTH($A13),"00")&"-"&TEXT(DAY($A13),"00"),history!$S:$S,">0"),0),IFERROR(1/_xlfn.MINIFS(history!$H:$H,history!$C:$C,"claro",history!$D:$D,"flex",history!$A:$A,YEAR($A13)&"-"&TEXT(MONTH($A13),"00")&"-"&TEXT(DAY($A13),"00")),0),IFERROR(1/_xlfn.MINIFS(history!$H:$H,history!$C:$C,"claro",history!$D:$D,"fit",history!$A:$A,YEAR($A13)&"-"&TEXT(MONTH($A13),"00")&"-"&TEXT(DAY($A13),"00"),history!$S:$S,"="),0)),"") -> 44.9
A14: 46206 | B14: =IFERROR(IF(_xlfn.MINIFS(history!$H:$H,history!$C:$C,"tim",history!$D:$D,"control",history!$A:$A,YEAR($A14)&"-"&TEXT(MONTH($A14),"00")&"-"&TEXT(DAY($A14),"00"))=0,"",_xlfn.MINIFS(history!$H:$H,history!$C:$C,"tim",history!$D:$D,"control",history!$A:$A,YEAR($A14)&"-"&TEXT(MONTH($A14),"00")&"-"&TEXT(DAY($A14),"00"))),"") -> 58.99 | C14: =IFERROR(IF(_xlfn.MINIFS(history!$H:$H,history!$C:$C,"vivo",history!$D:$D,"control",history!$A:$A,YEAR($A14)&"-"&TEXT(MONTH($A14),"00")&"-"&TEXT(DAY($A14),"00"))=0,"",_xlfn.MINIFS(history!$H:$H,history!$C:$C,"vivo",history!$D:$D,"control",history!$A:$A,YEAR($A14)&"-"&TEXT(MONTH($A14),"00")&"-"&TEXT(DAY($A14),"00"))),"") -> 59 | D14: =IFERROR(IF(_xlfn.MINIFS(history!$H:$H,history!$C:$C,"claro",history!$D:$D,"control",history!$A:$A,YEAR($A14)&"-"&TEXT(MONTH($A14),"00")&"-"&TEXT(DAY($A14),"00"))=0,"",_xlfn.MINIFS(history!$H:$H,history!$C:$C,"claro",history!$D:$D,"control",history!$A:$A,YEAR($A14)&"-"&TEXT(MONTH($A14),"00")&"-"&TEXT(DAY($A14),"00"))),"") -> 59.9 | E14: =IFERROR(IF(_xlfn.MINIFS(history!$H:$H,history!$C:$C,"tim",history!$D:$D,"postpaid",history!$A:$A,YEAR($A14)&"-"&TEXT(MONTH($A14),"00")&"-"&TEXT(DAY($A14),"00"))=0,"",_xlfn.MINIFS(history!$H:$H,history!$C:$C,"tim",history!$D:$D,"postpaid",history!$A:$A,YEAR($A14)&"-"&TEXT(MONTH($A14),"00")&"-"&TEXT(DAY($A14),"00"))),"") -> 119.99 | F14: =IFERROR(IF(_xlfn.MINIFS(history!$H:$H,history!$C:$C,"vivo",history!$D:$D,"postpaid",history!$A:$A,YEAR($A14)&"-"&TEXT(MONTH($A14),"00")&"-"&TEXT(DAY($A14),"00"))=0,"",_xlfn.MINIFS(history!$H:$H,history!$C:$C,"vivo",history!$D:$D,"postpaid",history!$A:$A,YEAR($A14)&"-"&TEXT(MONTH($A14),"00")&"-"&TEXT(DAY($A14),"00"))),"") -> 150 | G14: =IFERROR(IF(_xlfn.MINIFS(history!$H:$H,history!$C:$C,"claro",history!$D:$D,"postpaid",history!$A:$A,YEAR($A14)&"-"&TEXT(MONTH($A14),"00")&"-"&TEXT(DAY($A14),"00"))=0,"",_xlfn.MINIFS(history!$H:$H,history!$C:$C,"claro",history!$D:$D,"postpaid",history!$A:$A,YEAR($A14)&"-"&TEXT(MONTH($A14),"00")&"-"&TEXT(DAY($A14),"00"))),"") -> 124.9 | H14: =IFERROR(IF(_xlfn.MINIFS(history!$H:$H,history!$C:$C,"tim",history!$D:$D,"prepaid",history!$A:$A,YEAR($A14)&"-"&TEXT(MONTH($A14),"00")&"-"&TEXT(DAY($A14),"00"),history!$N:$N,">=28")=0,"",_xlfn.MINIFS(history!$H:$H,history!$C:$C,"tim",history!$D:$D,"prepaid",history!$A:$A,YEAR($A14)&"-"&TEXT(MONTH($A14),"00")&"-"&TEXT(DAY($A14),"00"),history!$N:$N,">=28")),"") -> 30 | I14: =IFERROR(IF(_xlfn.MINIFS(history!$H:$H,history!$C:$C,"vivo",history!$D:$D,"prepaid",history!$A:$A,YEAR($A14)&"-"&TEXT(MONTH($A14),"00")&"-"&TEXT(DAY($A14),"00"),history!$N:$N,">=28")=0,"",_xlfn.MINIFS(history!$H:$H,history!$C:$C,"vivo",history!$D:$D,"prepaid",history!$A:$A,YEAR($A14)&"-"&TEXT(MONTH($A14),"00")&"-"&TEXT(DAY($A14),"00"),history!$N:$N,">=28")),"") -> 30 | J14: =IFERROR(IF(_xlfn.MINIFS(history!$H:$H,history!$C:$C,"claro",history!$D:$D,"prepaid",history!$A:$A,YEAR($A14)&"-"&TEXT(MONTH($A14),"00")&"-"&TEXT(DAY($A14),"00"),history!$N:$N,">=28")=0,"",_xlfn.MINIFS(history!$H:$H,history!$C:$C,"claro",history!$D:$D,"prepaid",history!$A:$A,YEAR($A14)&"-"&TEXT(MONTH($A14),"00")&"-"&TEXT(DAY($A14),"00"),history!$N:$N,">=28")),"") -> 30 | K14: =IFERROR(1/MAX(IFERROR(1/_xlfn.MINIFS(history!$H:$H,history!$C:$C,"tim",history!$D:$D,"lite",history!$A:$A,YEAR($A14)&"-"&TEXT(MONTH($A14),"00")&"-"&TEXT(DAY($A14),"00"),history!$S:$S,">0"),0),IFERROR(1/_xlfn.MINIFS(history!$H:$H,history!$C:$C,"tim",history!$D:$D,"flex",history!$A:$A,YEAR($A14)&"-"&TEXT(MONTH($A14),"00")&"-"&TEXT(DAY($A14),"00")),0),IFERROR(1/_xlfn.MINIFS(history!$H:$H,history!$C:$C,"tim",history!$D:$D,"fit",history!$A:$A,YEAR($A14)&"-"&TEXT(MONTH($A14),"00")&"-"&TEXT(DAY($A14),"00"),history!$S:$S,"="),0)),"") | L14: =IFERROR(1/MAX(IFERROR(1/_xlfn.MINIFS(history!$H:$H,history!$C:$C,"vivo",history!$D:$D,"lite",history!$A:$A,YEAR($A14)&"-"&TEXT(MONTH($A14),"00")&"-"&TEXT(DAY($A14),"00"),history!$S:$S,">0"),0),IFERROR(1/_xlfn.MINIFS(history!$H:$H,history!$C:$C,"vivo",history!$D:$D,"flex",history!$A:$A,YEAR($A14)&"-"&TEXT(MONTH($A14),"00")&"-"&TEXT(DAY($A14),"00")),0),IFERROR(1/_xlfn.MINIFS(history!$H:$H,history!$C:$C,"vivo",history!$D:$D,"fit",history!$A:$A,YEAR($A14)&"-"&TEXT(MONTH($A14),"00")&"-"&TEXT(DAY($A14),"00"),history!$S:$S,"="),0)),"") -> 45 | M14: =IFERROR(1/MAX(IFERROR(1/_xlfn.MINIFS(history!$H:$H,history!$C:$C,"claro",history!$D:$D,"lite",history!$A:$A,YEAR($A14)&"-"&TEXT(MONTH($A14),"00")&"-"&TEXT(DAY($A14),"00"),history!$S:$S,">0"),0),IFERROR(1/_xlfn.MINIFS(history!$H:$H,history!$C:$C,"claro",history!$D:$D,"flex",history!$A:$A,YEAR($A14)&"-"&TEXT(MONTH($A14),"00")&"-"&TEXT(DAY($A14),"00")),0),IFERROR(1/_xlfn.MINIFS(history!$H:$H,history!$C:$C,"claro",history!$D:$D,"fit",history!$A:$A,YEAR($A14)&"-"&TEXT(MONTH($A14),"00")&"-"&TEXT(DAY($A14),"00"),history!$S:$S,"="),0)),"") -> 44.9
... A24: 46216 | B24: =IFERROR(IF(_xlfn.MINIFS(history!$H:$H,history!$C:$C,"tim",history!$D:$D,"control",history!$A:$A,YEAR($A24)&"-"&TEXT(MONTH($A24),"00")&"-"&TEXT(DAY($A24),"00"))=0,"",_xlfn.MINIFS(history!$H:$H,history!$C:$C,"tim",history!$D:$D,"control",history!$A:$A,YEAR($A24)&"-"&TEXT(MONTH($A24),"00")&"-"&TEXT(DAY($A24),"00"))),"") -> 49.99 | C24: =IFERROR(IF(_xlfn.MINIFS(history!$H:$H,history!$C:$C,"vivo",history!$D:$D,"control",history!$A:$A,YEAR($A24)&"-"&TEXT(MONTH($A24),"00")&"-"&TEXT(DAY($A24),"00"))=0,"",_xlfn.MINIFS(history!$H:$H,history!$C:$C,"vivo",history!$D:$D,"control",history!$A:$A,YEAR($A24)&"-"&TEXT(MONTH($A24),"00")&"-"&TEXT(DAY($A24),"00"))),"") -> 59 | D24: =IFERROR(IF(_xlfn.MINIFS(history!$H:$H,history!$C:$C,"claro",history!$D:$D,"control",history!$A:$A,YEAR($A24)&"-"&TEXT(MONTH($A24),"00")&"-"&TEXT(DAY($A24),"00"))=0,"",_xlfn.MINIFS(history!$H:$H,history!$C:$C,"claro",history!$D:$D,"control",history!$A:$A,YEAR($A24)&"-"&TEXT(MONTH($A24),"00")&"-"&TEXT(DAY($A24),"00"))),"") -> 59.9 | E24: =IFERROR(IF(_xlfn.MINIFS(history!$H:$H,history!$C:$C,"tim",history!$D:$D,"postpaid",history!$A:$A,YEAR($A24)&"-"&TEXT(MONTH($A24),"00")&"-"&TEXT(DAY($A24),"00"))=0,"",_xlfn.MINIFS(history!$H:$H,history!$C:$C,"tim",history!$D:$D,"postpaid",history!$A:$A,YEAR($A24)&"-"&TEXT(MONTH($A24),"00")&"-"&TEXT(DAY($A24),"00"))),"") -> 119.99 | F24: =IFERROR(IF(_xlfn.MINIFS(history!$H:$H,history!$C:$C,"vivo",history!$D:$D,"postpaid",history!$A:$A,YEAR($A24)&"-"&TEXT(MONTH($A24),"00")&"-"&TEXT(DAY($A24),"00"))=0,"",_xlfn.MINIFS(history!$H:$H,history!$C:$C,"vivo",history!$D:$D,"postpaid",history!$A:$A,YEAR($A24)&"-"&TEXT(MONTH($A24),"00")&"-"&TEXT(DAY($A24),"00"))),"") -> 150 | G24: =IFERROR(IF(_xlfn.MINIFS(history!$H:$H,history!$C:$C,"claro",history!$D:$D,"postpaid",history!$A:$A,YEAR($A24)&"-"&TEXT(MONTH($A24),"00")&"-"&TEXT(DAY($A24),"00"))=0,"",_xlfn.MINIFS(history!$H:$H,history!$C:$C,"claro",history!$D:$D,"postpaid",history!$A:$A,YEAR($A24)&"-"&TEXT(MONTH($A24),"00")&"-"&TEXT(DAY($A24),"00"))),"") -> 124.9 | H24: =IFERROR(IF(_xlfn.MINIFS(history!$H:$H,history!$C:$C,"tim",history!$D:$D,"prepaid",history!$A:$A,YEAR($A24)&"-"&TEXT(MONTH($A24),"00")&"-"&TEXT(DAY($A24),"00"),history!$N:$N,">=28")=0,"",_xlfn.MINIFS(history!$H:$H,history!$C:$C,"tim",history!$D:$D,"prepaid",history!$A:$A,YEAR($A24)&"-"&TEXT(MONTH($A24),"00")&"-"&TEXT(DAY($A24),"00"),history!$N:$N,">=28")),"") -> 30 | I24: =IFERROR(IF(_xlfn.MINIFS(history!$H:$H,history!$C:$C,"vivo",history!$D:$D,"prepaid",history!$A:$A,YEAR($A24)&"-"&TEXT(MONTH($A24),"00")&"-"&TEXT(DAY($A24),"00"),history!$N:$N,">=28")=0,"",_xlfn.MINIFS(history!$H:$H,history!$C:$C,"vivo",history!$D:$D,"prepaid",history!$A:$A,YEAR($A24)&"-"&TEXT(MONTH($A24),"00")&"-"&TEXT(DAY($A24),"00"),history!$N:$N,">=28")),"") -> 30 | J24: =IFERROR(IF(_xlfn.MINIFS(history!$H:$H,history!$C:$C,"claro",history!$D:$D,"prepaid",history!$A:$A,YEAR($A24)&"-"&TEXT(MONTH($A24),"00")&"-"&TEXT(DAY($A24),"00"),history!$N:$N,">=28")=0,"",_xlfn.MINIFS(history!$H:$H,history!$C:$C,"claro",history!$D:$D,"prepaid",history!$A:$A,YEAR($A24)&"-"&TEXT(MONTH($A24),"00")&"-"&TEXT(DAY($A24),"00"),history!$N:$N,">=28")),"") -> 30 | K24: =IFERROR(1/MAX(IFERROR(1/_xlfn.MINIFS(history!$H:$H,history!$C:$C,"tim",history!$D:$D,"lite",history!$A:$A,YEAR($A24)&"-"&TEXT(MONTH($A24),"00")&"-"&TEXT(DAY($A24),"00"),history!$S:$S,">0"),0),IFERROR(1/_xlfn.MINIFS(history!$H:$H,history!$C:$C,"tim",history!$D:$D,"flex",history!$A:$A,YEAR($A24)&"-"&TEXT(MONTH($A24),"00")&"-"&TEXT(DAY($A24),"00")),0),IFERROR(1/_xlfn.MINIFS(history!$H:$H,history!$C:$C,"tim",history!$D:$D,"fit",history!$A:$A,YEAR($A24)&"-"&TEXT(MONTH($A24),"00")&"-"&TEXT(DAY($A24),"00"),history!$S:$S,"="),0)),"") -> 35 | L24: =IFERROR(1/MAX(IFERROR(1/_xlfn.MINIFS(history!$H:$H,history!$C:$C,"vivo",history!$D:$D,"lite",history!$A:$A,YEAR($A24)&"-"&TEXT(MONTH($A24),"00")&"-"&TEXT(DAY($A24),"00"),history!$S:$S,">0"),0),IFERROR(1/_xlfn.MINIFS(history!$H:$H,history!$C:$C,"vivo",history!$D:$D,"flex",history!$A:$A,YEAR($A24)&"-"&TEXT(MONTH($A24),"00")&"-"&TEXT(DAY($A24),"00")),0),IFERROR(1/_xlfn.MINIFS(history!$H:$H,history!$C:$C,"vivo",history!$D:$D,"fit",history!$A:$A,YEAR($A24)&"-"&TEXT(MONTH($A24),"00")&"-"&TEXT(DAY($A24),"00"),history!$S:$S,"="),0)),"") -> 45 | M24: =IFERROR(1/MAX(IFERROR(1/_xlfn.MINIFS(history!$H:$H,history!$C:$C,"claro",history!$D:$D,"lite",history!$A:$A,YEAR($A24)&"-"&TEXT(MONTH($A24),"00")&"-"&TEXT(DAY($A24),"00"),history!$S:$S,">0"),0),IFERROR(1/_xlfn.MINIFS(history!$H:$H,history!$C:$C,"claro",history!$D:$D,"flex",history!$A:$A,YEAR($A24)&"-"&TEXT(MONTH($A24),"00")&"-"&TEXT(DAY($A24),"00")),0),IFERROR(1/_xlfn.MINIFS(history!$H:$H,history!$C:$C,"claro",history!$D:$D,"fit",history!$A:$A,YEAR($A24)&"-"&TEXT(MONTH($A24),"00")&"-"&TEXT(DAY($A24),"00"),history!$S:$S,"="),0)),"") -> 44.9
A26: Rows = day: each cell = cheapest R$ that carrier offered in the category on that snapshot_date — a live MINIFS over `history` matching the EXACT date (a locale-safe text date built from the row's date, since history stores dates as TEXT — CONTEXT §7). Pre = cheapest 30-day prepaid plan (validity_days >= 28; pre-#18 dates have no validity → blank, fills from 26-Jun on). Digital = min of Vivo Lite / Claro Flex / TIM Fit — no-commitment versions only (lite: the Sem-fidelidade price of toggle cards, #26; fit: the Mensal version, #28). Heatmap = per-category-block green→yellow (each cell vs all carriers in its category; subtle while prices are near-flat, differentiates as they move). Grows one row per day; charts on the `Charts` sheet.
A27: Post — TIM: the entry-level tracked is the cheapest postpaid plan, R$119,99 — note it is CREDIT-CARD-only ("no cartão"; TIM's Express line); the cheapest bill-payment ("na fatura") plan is R$129,99. Both are in `history` + the TIM sheet, with the billing type in `payment_method` — a price change on the tracked plan shows in `changes` and the daily alert.

Sheet Charts
A1: Price evolution — cheapest R$ per carrier × category, by day (source: `comparison`)
P37: Latest-day price (bar source) | Q37: TIM | R37: Vivo | S37: Claro
P38: Control | Q38: =IF('comparison'!B24="",NA(),'comparison'!B24) | R38: =IF('comparison'!C24="",NA(),'comparison'!C24) | S38: =IF('comparison'!D24="",NA(),'comparison'!D24)
P39: Post | Q39: =IF('comparison'!E24="",NA(),'comparison'!E24) | R39: =IF('comparison'!F24="",NA(),'comparison'!F24) | S39: =IF('comparison'!G24="",NA(),'comparison'!G24)
P40: Pre | Q40: =IF('comparison'!H24="",NA(),'comparison'!H24) | R40: =IF('comparison'!I24="",NA(),'comparison'!I24) | S40: =IF('comparison'!J24="",NA(),'comparison'!J24)
P41: Digital | Q41: =IF('comparison'!K24="",NA(),'comparison'!K24) | R41: =IF('comparison'!L24="",NA(),'comparison'!L24) | S41: =IF('comparison'!M24="",NA(),'comparison'!M24)

Sheet Ranking
A1: Ranking (today) — within category, aligned by price rank
A3: Pure Postpaid
A4: Rank | B4: Vivo R$ | C4: Claro R$ | D4: TIM R$ | E4: Vivo plan | F4: Claro plan | G4: TIM plan
A5: 1 | B5: 150 | C5: 124.9 | D5: 119.99 | E5: Vivo Pós com Amazon (60GB) | F5: Pós 60GB (60GB) | G5: TIM Black A Express 67GB (67GB)
A6: 2 | B6: 165 | C6: 164.9 | D6: 129.99 | E6: Vivo Pós com Globoplay (60GB) | F6: Pós 50GB com GeForce NOW (50GB) | G6: TIM Black 70GB (70GB)
A7: 3 | B7: 165 | C7: 179.9 | D7: 144.99 | E7: Vivo Pós com Spotify (60GB) | F7: Pós 100GB (100GB) | G7: TIM Black B Express 82GB (82GB)
A8: 4 | B8: 180 | C8: 239.9 | D8: 149.99 | E8: Vivo Pós com Disney+ (60GB) | F8: Pós 150GB (150GB) | G8: TIM Black Plus 80GB (80GB)
A9: 5 | B9: 180 | C9: 339.9 | D9: 159.99 | E9: Vivo Pós com Netflix (60GB) | F9: Pós 200GB (200GB) | G9: TIM Black C Ultra 95GB (95GB)
A10: 6 | B10: 180 | D10: 159.99 | E10: Vivo Pós com Premiere (60GB) | G10: TIM Black Premium 110GB (110GB)
A11: 7 | B11: 215 | D11: 164.99 | E11: Vivo Pós com Travel (70GB) | G11: TIM Black C Express 107GB (107GB)
A13: Control / Hybrid
A14: Rank | B14: Vivo R$ | C14: Claro R$ | D14: TIM R$ | E14: Vivo plan | F14: Claro plan | G14: TIM plan
A15: 1 | B15: 59 | C15: 59.9 | D15: 49.99 | E15: Vivo Controle (46GB) | F15: Controle 25GB (25GB) · promo R$54.9 | G15: TIM Controle 41GB (41GB)
A16: 2 | B16: 80 | C16: 69.9 | D16: 59.99 | E16: Vivo Controle (61GB) | F16: Controle 30GB (30GB) | G16: TIM Controle Plus 45GB (45GB)
A17: 3 | B17: 90 | C17: 99.9 | D17: 60.99 | E17: Vivo Controle Educação (61GB) | F17: Controle 30GB (30GB) | G17: TIM Controle Light Express 31GB (31GB)
A18: 4 | B18: 90 | D18: 64.99 | E18: Vivo Controle Música (61GB) | G18: TIM Controle Pro Express
A19: 5 | B19: 90 | D19: 69.99 | E19: Vivo Controle Saúde (61GB) | G19: TIM Controle Premium 53GB (53GB)
A20: 6 | B20: 95 | E20: Vivo Controle Netflix (61GB)
A21: 7 | B21: 110 | E21: Vivo Controle Entretenimento (61GB)
A23: Prepaid
A24: Note: prepaid is not a clean unit — Claro Prezão is a daily fee (R$1/dia) vs Vivo/TIM recharge amounts.
A25: Rank | B25: Vivo R$ | C25: Claro R$ | D25: TIM R$ | E25: Vivo plan | F25: Claro plan | G25: TIM plan
A26: 1 | B26: 17 | C26: 15 | D26: 20 | E26: Vivo Pré (4GB) | F26: Prezão 4GB (12 dias) (4GB) | G26: TIM Pré XIP Plus 6GB (6GB)
A27: 2 | B27: 20 | C27: 15 | D27: 25 | E27: Vivo Pré (5GB) | F27: Prezão 5GB (15 dias) (5GB) | G27: TIM Pré XIP Plus 8GB (8GB)
A28: 3 | B28: 25 | C28: 20 | D28: 30 | E28: Vivo Pré (9GB) | F28: Prezão 6GB (20 dias) (6GB) | G28: TIM Pré XIP Plus 16GB (16GB)
A29: 4 | B29: 30 | C29: 20 | E29: Vivo Pré (25GB) | F29: Prezão 8GB (20 dias) (8GB)
A30: 5 | C30: 25 | F30: Prezão 10GB (25 dias) (10GB)
A31: 6 | C31: 25 | F31: Prezão 9GB (25 dias) (9GB)
A32: 7 | C32: 30 | F32: Prezão 12GB (30 dias) (12GB)
A34: Digital
A35: Digital = Vivo Lite + Claro Flex + TIM Fit (#28); entry-level = no-commitment versions.
A36: Rank | B36: Vivo R$ | C36: Claro R$ | D36: TIM R$ | E36: Vivo plan | F36: Claro plan | G36: TIM plan
A37: 1 | B37: 35 | C37: 44.9 | D37: 35 | E37: Easy Lite (20GB) | F37: Flex 15GB (15GB) | G37: TIM Controle Fit Mensal (20GB)
A38: 2 | B38: 45 | C38: 59.9 | E38: Easy Lite (30GB) · promo R$30 | F38: Flex 20GB (20GB)
A39: 3 | B39: 55 | C39: 69.9 | E39: Easy Lite (40GB) · promo R$40 | F39: Flex 30GB (30GB)
A40: 4 | C40: 119.9 | F40: Flex 40GB (40GB)

Sheet Vivo
A1: Plan | B1: Price R$ | C1: Promo R$ | D1: Data | E1: Voice | F1: Unlimited apps | G1: Streaming | H1: Notes
A2: Postpaid
A3: Vivo Pós com Amazon | B3: 150 | D3: 60 GB (50 GB de franquia 10 GB de bônus) | H3: Assinatura Amazon Prime inclusa
A4: Vivo Pós com Globoplay | B4: 165 | D4: 60 GB (50 GB de franquia 10 GB de bônus) | G4: Globoplay | H4: Assinatura Globoplay inclusa
A5: Vivo Pós com Spotify | B5: 165 | D5: 60 GB (50 GB de franquia 10 GB de bônus) | G5: Spotify | H5: Assinatura Spotify Premium inclusa
A6: Vivo Pós com Disney+ | B6: 180 | D6: 60 GB (50 GB de franquia 10 GB de bônus) | G6: Disney+ | H6: Assinatura Disney+ Padrão inclusa
A7: Vivo Pós com Netflix | B7: 180 | D7: 60 GB (50 GB de franquia 10 GB de bônus) | G7: Netflix | H7: Assinatura Netflix Padrão inclusa
A8: Vivo Pós com Premiere | B8: 180 | D8: 60 GB (50 GB de franquia 10 GB de bônus) | G8: Premiere | H8: Assinatura Premiere inclusa
A9: Vivo Pós com Travel | B9: 215 | D9: 70 GB (60 GB de franquia 10 GB de bônus) | H9: 2 meses de YouTube sem consumo no plano
A10: Control
A11: Vivo Controle | B11: 59 | D11: 46 GB (15 GB de franquia 31 GB de bônus) | H11: 2 meses de YouTube sem consumo no plano
A12: Vivo Controle | B12: 80 | D12: 61 GB (20 GB de franquia 31 GB de bônus) | H12: 2 meses de YouTube sem consumo no plano
A13: Vivo Controle Educação | B13: 90 | D13: 61 GB (20 GB de franquia 31 GB de bônus) | H13: Assinatura Vivae inclusa
A14: Vivo Controle Música | B14: 90 | D14: 61 GB (20 GB de franquia 31 GB de bônus) | H14: Apple Music Individual
A15: Vivo Controle Saúde | B15: 90 | D15: 61 GB (20 GB de franquia 31 GB de bônus) | H15: Assinatura Vale Saúde Sempre inclusa
A16: Vivo Controle Netflix | B16: 95 | D16: 61 GB (20 GB de franquia 31 GB de bônus) | H16: Assinatura Netflix Padrão com anúncios
A17: Vivo Controle Entretenimento | B17: 110 | D17: 61 GB (20 GB de franquia 31 GB de bônus) | H17: Assinatura Vivo TV Inicial inclusa
A18: Digital
A19: Easy Lite | B19: 35 | D19: 20 GB (20 GB de franquia) | H19: 2 meses de YouTube sem consumo no plano
A20: Easy Lite | B20: 45 | C20: 30 | D20: 30 GB (30 GB de franquia) | H20: 2 meses de YouTube sem consumo no plano · preço sem fidelidade; fidelidade 12m no promo
A21: Easy Lite | B21: 55 | C21: 40 | D21: 40 GB (40 GB de franquia) | H21: 2 meses de YouTube sem consumo no plano · preço sem fidelidade; fidelidade 12m no promo
A22: Prepaid
A23: Vivo Pré | B23: 17 | D23: 4 GB (4 GB para navegar como quiser) · 15d
A24: Vivo Pré | B24: 20 | D24: 5 GB (5 GB para navegar como quiser) · 17d
A25: Vivo Pré | B25: 25 | D25: 9 GB (6 GB para navegar como quiser 3 GB para navegar no YouTube) · 22d
A26: Vivo Pré | B26: 30 | D26: 25 GB (15 GB para navegar como quiser 5 GB de bônus 5 GB para navegar no Youtube) · 30d

Sheet Claro
A1: Plan | B1: Price R$ | C1: Promo R$ | D1: Data | E1: Voice | F1: Unlimited apps | G1: Streaming | H1: Notes
A2: Postpaid
A3: Pós 60GB | B3: 124.9 | D3: 60 GB | F3: WhatsApp | H3: Armazenamento na nuvem:; Google One ou iCloud+; WhatsApp ilimitado; Roaming: Passaporte Américas; Claro Sync: Smartwatch conectado
A4: Pós 50GB com GeForce NOW | B4: 164.9 | D4: 50 GB | F4: WhatsApp | H4: Armazenamento na nuvem:; Google One ou iCloud+; WhatsApp ilimitado; Roaming: Passaporte Américas; Claro Sync: Smartwatch conectado; Inclusa assinatura GeForce NOW
A5: Pós 100GB | B5: 179.9 | D5: 100 GB | F5: WhatsApp | H5: Armazenamento na nuvem:; Google One ou iCloud+; WhatsApp ilimitado; Roaming: Passaporte Américas; Claro Sync: Smartwatch conectado
A6: Pós 150GB | B6: 239.9 | D6: 150 GB | F6: WhatsApp | H6: Armazenamento na nuvem:; Google One ou iCloud+; WhatsApp ilimitado; Roaming: Passaporte Américas e Europa; Claro Sync: Smartwatch conectado
A7: Pós 200GB | B7: 339.9 | D7: 200 GB | F7: WhatsApp | H7: Armazenamento na nuvem:; Google One ou iCloud+; WhatsApp ilimitado; Roaming: Passaporte Mundo; Claro Sync: Smartwatch conectado
A8: Control
A9: Controle 25GB | B9: 59.9 | C9: 54.9 | D9: 25 GB | F9: WhatsApp | H9: Para uso livre; Para redes sociais e vídeos; Bônus exclusivo; Aproveite na sua franquia; WhatsApp e ligações ilimitadas · De R$ 59,90 Por:
A10: Controle 30GB | B10: 69.9 | D10: 30 GB | F10: WhatsApp | H10: Para uso livre; Bônus especial para uso livre; Bônus para redes sociais e apps; Redes sociais e apps; WhatsApp ilimitado
A11: Controle 30GB | B11: 99.9 | D11: 30 GB | F11: WhatsApp | H11: Para uso livre; Bônus para redes sociais e apps; Bônus uso livre; Redes sociais e apps; WhatsApp ilimitado
A12: Digital
A13: Flex 15GB | B13: 44.9 | D13: 15 GB | F13: WhatsApp | H13: Para uso livre; Bônus especial para uso livre; Para redes sociais e apps; Bônus extra nos apps; WhatsApp ilimitado
A14: Flex 20GB | B14: 59.9 | D14: 20 GB | F14: WhatsApp | H14: Para uso livre; Bônus especial para uso livre; Para redes sociais e apps; Bônus extra nos apps; WhatsApp ilimitado
A15: Flex 30GB | B15: 69.9 | D15: 30 GB | F15: WhatsApp | H15: Para uso livre; Bônus especial para uso livre; Para redes sociais e apps; Bônus extra nos apps; WhatsApp ilimitado; Assinatura Claro musica inclusa
A16: Flex 40GB | B16: 119.9 | D16: 40 GB | F16: WhatsApp | H16: Para uso livre; Para redes sociais e apps; Bônus uso livre; Bônus extra nos apps; WhatsApp ilimitado; Assinatura Claro musica inclusa
A17: Prepaid
A18: Prezão 4GB (12 dias) | B18: 15 | D18: 4 GB · 12d | H18: recarga Prezão R$15 — validade 12 dias
A19: Prezão 5GB (15 dias) | B19: 15 | D19: 5 GB · 15d | H19: recarga Prezão R$15 — validade 15 dias
A20: Prezão 6GB (20 dias) | B20: 20 | D20: 6 GB · 20d | H20: recarga Prezão R$20 — validade 20 dias
A21: Prezão 8GB (20 dias) | B21: 20 | D21: 8 GB · 20d | H21: recarga Prezão R$20 — validade 20 dias
A22: Prezão 10GB (25 dias) | B22: 25 | D22: 10 GB · 25d | H22: recarga Prezão R$25 — validade 25 dias
A23: Prezão 9GB (25 dias) | B23: 25 | D23: 9 GB · 25d | H23: recarga Prezão R$25 — validade 25 dias
A24: Prezão 12GB (30 dias) | B24: 30 | D24: 12 GB · 30d | H24: recarga Prezão R$30 — validade 30 dias

Sheet TIM
A1: Plan | B1: Price R$ | C1: Promo R$ | D1: Data | E1: Voice | F1: Unlimited apps | G1: Streaming | H1: Notes
A2: Postpaid
A3: TIM Black A Express 67GB | B3: 119.99 | D3: 67 GB
A4: TIM Black 70GB | B4: 129.99 | D4: 70 GB
A5: TIM Black B Express 82GB | B5: 144.99 | D5: 82 GB
A6: TIM Black Plus 80GB | B6: 149.99 | D6: 80 GB
A7: TIM Black C Ultra 95GB | B7: 159.99 | D7: 95 GB
A8: TIM Black Premium 110GB | B8: 159.99 | D8: 110 GB
A9: TIM Black C Express 107GB | B9: 164.99 | D9: 107 GB
A10: Control
A11: TIM Controle 41GB | B11: 49.99 | D11: 41 GB
A12: TIM Controle Plus 45GB | B12: 59.99 | D12: 45 GB
A13: TIM Controle Light Express 31GB | B13: 60.99 | D13: 31 GB
A14: TIM Controle Pro Express | B14: 64.99
A15: TIM Controle Premium 53GB | B15: 69.99 | D15: 53 GB
A16: Digital
A17: TIM Controle Fit Anual | B17: 30 | D17: 30 GB | H17: plano anual 12x no cartão de crédito; prazo de permanência 12m
A18: TIM Controle Fit Mensal | B18: 35 | D18: 20 GB | H18: plano mensal, sem prazo de permanência
A19: Prepaid
A20: TIM Pré XIP Plus 6GB | B20: 20 | D20: 6 GB · 17d
A21: TIM Pré XIP Plus 8GB | B21: 25 | D21: 8 GB · 22d
A22: TIM Pré XIP Plus 16GB | B22: 30 | D22: 16 GB · 30d
